[
  {
    "sku_id": "nike-IB8954-200-Velvet_Brown/Velvet_Brown/Metallic_Gold",
    "brand": "NIKE",
    "parent_id": "IB8954-200",
    "sku_url": "https://www.nike.com/tw/t/air-rift-Cn9A0eWh/IB8954-200",
    "category": "woman_shoes",
    "product_name": "Nike Air Rift",
    "img_path": "https://static.nike.com/a/images/t_default/749b4251-2b08-437a-b9b3-30afd9585211/WMNS+NIKE+AIR+RIFT.png",
    "color_label": "Velvet Brown/Velvet Brown/Metallic Gold",
    "original_price": null,
    "current_price": 4300,
    "full_size_list": [
      "CM 22",
      "CM 23",
      "CM 24",
      "CM 25",
      "CM 26",
      "CM 27"
    ],
    "available_list": [
      "CM 22",
      "CM 23",
      "CM 24",
      "CM 25",
      "CM 26"
    ]
  },
  {
    "sku_id": "nike-IH0388-200-Mink_Brown/Light_Bone/College_Grey/Mink_Brown",
    "brand": "NIKE",
    "parent_id": "IH0388-200",
    "sku_url": "https://www.nike.com/tw/t/v2k-run-43YfLxpv/IH0388-200",
    "category": "woman_shoes",
    "product_name": "Nike V2K Run",
    "img_path": "https://static.nike.com/a/images/t_default/u_9ddf04c7-2a9a-4d76-add1-d15af8f0263d,c_scale,fl_relative,w_1.0,h_1.0,fl_layer_apply/9e9ce246-bbe7-475f-b3de-c84199d1d905/W+NIKE+V2K+RUN.png",
    "color_label": "Mink Brown/Light Bone/College Grey/Mink Brown",
    "original_price": null,
    "current_price": 4000,
    "full_size_list": [
      "CM 22",
      "CM 22.5",
      "CM 23",
      "CM 23.5",
      "CM 24",
      "CM 24.5",
      "CM 25",
      "CM 25.5",
      "CM 26",
      "CM 26.5",
      "CM 27"
    ],
    "available_list": [
      "CM 22",
      "CM 22.5",
      "CM 23",
      "CM 23.5",
      "CM 24",
      "CM 24.5",
      "CM 25",
      "CM 25.5",
      "CM 26",
      "CM 26.5"
    ]
  },
  {
    "sku_id": "nike-IH0388-001-黑色/Metallic_Silver/Anthracite/黑色",
    "brand": "NIKE",
    "parent_id": "IH0388-001",
    "sku_url": "https://www.nike.com/tw/t/v2k-run-43YfLxpv/IH0388-001",
    "category": "woman_shoes",
    "product_name": "Nike V2K Run",
    "img_path": "https://static.nike.com/a/images/t_default/u_9ddf04c7-2a9a-4d76-add1-d15af8f0263d,c_scale,fl_relative,w_1.0,h_1.0,fl_layer_apply/6bdcec5b-396c-4e6e-a96c-617206e53eca/W+NIKE+V2K+RUN.png",
    "color_label": "黑色/Metallic Silver/Anthracite/黑色",
    "original_price": null,
    "current_price": 4000,
    "full_size_list": [
      "CM 22",
      "CM 22.5",
      "CM 23",
      "CM 23.5",
      "CM 24",
      "CM 24.5",
      "CM 25",
      "CM 25.5",
      "CM 26",
      "CM 26.5",
      "CM 27"
    ],
    "available_list": [
      "CM 22",
      "CM 22.5",
      "CM 23",
      "CM 23.5",
      "CM 24",
      "CM 24.5",
      "CM 25",
      "CM 25.5",
      "CM 26",
      "CM 26.5",
      "CM 27"
    ]
  },
  {
    "sku_id": "nike-IH0388-002-Cool_Grey/Wolf_Grey/Photon_Dust/Metallic_Silver",
    "brand": "NIKE",
    "parent_id": "IH0388-002",
    "sku_url": "https://www.nike.com/tw/t/v2k-run-43YfLxpv/IH0388-002",
    "category": "woman_shoes",
    "product_name": "Nike V2K Run",
    "img_path": "https://static.nike.com/a/images/t_default/u_9ddf04c7-2a9a-4d76-add1-d15af8f0263d,c_scale,fl_relative,w_1.0,h_1.0,fl_layer_apply/84e11791-a94d-4aa8-b28a-0073d42f62e8/W+NIKE+V2K+RUN.png",
    "color_label": "Cool Grey/Wolf Grey/Photon Dust/Metallic Silver",
    "original_price": null,
    "current_price": 4000,
    "full_size_list": [
      "CM 22",
      "CM 22.5",
      "CM 23",
      "CM 23.5",
      "CM 24",
      "CM 24.5",
      "CM 25",
      "CM 25.5",
      "CM 26",
      "CM 26.5",
      "CM 27"
    ],
    "available_list": [
      "CM 22",
      "CM 22.5",
      "CM 23",
      "CM 23.5",
      "CM 24",
      "CM 24.5",
      "CM 25",
      "CM 25.5",
      "CM 26",
      "CM 26.5",
      "CM 27"
    ]
  },
  {
    "sku_id": "nike-HJ4292-001-黑色/Metallic_Silver",
    "brand": "NIKE",
    "parent_id": "HJ4292-001",
    "sku_url": "https://www.nike.com/tw/t/air-jordan-mule-9PAPEZZZ/HJ4292-001",
    "category": "woman_shoes",
    "product_name": "Air Jordan Mule",
    "img_path": "https://static.nike.com/a/images/t_default/u_126ab356-44d8-4a06-89b4-fcdcc8df0245,c_scale,fl_relative,w_1.0,h_1.0,fl_layer_apply/b316cffb-984b-45e9-aa3f-8f501a43bb3b/WMNS+AIR+JORDAN+MULE.png",
    "color_label": "黑色/Metallic Silver",
    "original_price": null,
    "current_price": 4900,
    "full_size_list": [
      "CM 22",
      "5.5",
      "CM 23",
      "6.5",
      "CM 24",
      "7.5",
      "CM 25",
      "8.5",
      "CM 26",
      "9.5",
      "CM 27",
      "10.5",
      "CM 28",
      "11.5",
      "CM 29"
    ],
    "available_list": [
      "CM 22",
      "CM 23",
      "CM 24",
      "CM 25",
      "CM 26",
      "CM 27"
    ]
  },
  {
    "sku_id": "nike-HJ4292-302-Luminous_Green/Metallic_Silver",
    "brand": "NIKE",
    "parent_id": "HJ4292-302",
    "sku_url": "https://www.nike.com/tw/t/air-jordan-mule-9PAPEZZZ/HJ4292-302",
    "category": "woman_shoes",
    "product_name": "Air Jordan Mule",
    "img_path": "https://static.nike.com/a/images/t_default/u_126ab356-44d8-4a06-89b4-fcdcc8df0245,c_scale,fl_relative,w_1.0,h_1.0,fl_layer_apply/ac880112-1c44-4128-b46c-e5a703dbb89f/WMNS+AIR+JORDAN+MULE.png",
    "color_label": "Luminous Green/Metallic Silver",
    "original_price": null,
    "current_price": 4900,
    "full_size_list": [
      "CM 22",
      "CM 22.5",
      "CM 23",
      "CM 23.5",
      "CM 24",
      "CM 24.5",
      "CM 25",
      "CM 25.5",
      "CM 26",
      "CM 26.5",
      "CM 27",
      "CM 27.5",
      "CM 28",
      "CM 28.5",
      "CM 29"
    ],
    "available_list": [
      "CM 23",
      "CM 24",
      "CM 25",
      "CM 26",
      "CM 27",
      "CM 28"
    ]
  },
  {
    "sku_id": "nike-HJ4292-300-Malachite/Metallic_Silver",
    "brand": "NIKE",
    "parent_id": "HJ4292-300",
    "sku_url": "https://www.nike.com/tw/t/air-jordan-mule-9PAPEZZZ/HJ4292-300",
    "category": "woman_shoes",
    "product_name": "Air Jordan Mule",
    "img_path": "https://static.nike.com/a/images/t_default/u_126ab356-44d8-4a06-89b4-fcdcc8df0245,c_scale,fl_relative,w_1.0,h_1.0,fl_layer_apply/6da0e081-e0aa-4dcd-8f2f-4c57649826f5/WMNS+AIR+JORDAN+MULE.png",
    "color_label": "Malachite/Metallic Silver",
    "original_price": null,
    "current_price": 4900,
    "full_size_list": [
      "CM 22",
      "CM 23",
      "CM 24",
      "CM 25",
      "CM 26",
      "CM 27",
      "CM 28"
    ],
    "available_list": [
      "CM 22",
      "CM 23",
      "CM 24",
      "CM 25",
      "CM 26",
      "CM 27"
    ]
  },
  {
    "sku_id": "nike-HJ4292-100-Summit_White/黑色/Metallic_Silver",
    "brand": "NIKE",
    "parent_id": "HJ4292-100",
    "sku_url": "https://www.nike.com/tw/t/air-jordan-mule-9PAPEZZZ/HJ4292-100",
    "category": "woman_shoes",
    "product_name": "Air Jordan Mule",
    "img_path": "https://static.nike.com/a/images/t_default/u_126ab356-44d8-4a06-89b4-fcdcc8df0245,c_scale,fl_relative,w_1.0,h_1.0,fl_layer_apply/2bb7eb13-0076-47af-bad3-0a07dc2e15cf/WMNS+AIR+JORDAN+MULE.png",
    "color_label": "Summit White/黑色/Metallic Silver",
    "original_price": null,
    "current_price": 4900,
    "full_size_list": [
      "CM 22",
      "CM 23",
      "CM 24",
      "CM 25",
      "CM 26",
      "CM 27"
    ],
    "available_list": [
      "CM 23",
      "CM 24",
      "CM 25",
      "CM 26",
      "CM 27"
    ]
  },
  {
    "sku_id": "nike-HJ4292-600-Dark_Team_Red/Burgundy_Crush/Metallic_Silver",
    "brand": "NIKE",
    "parent_id": "HJ4292-600",
    "sku_url": "https://www.nike.com/tw/t/air-jordan-mule-9PAPEZZZ/HJ4292-600",
    "category": "woman_shoes",
    "product_name": "Air Jordan Mule",
    "img_path": "https://static.nike.com/a/images/t_default/u_126ab356-44d8-4a06-89b4-fcdcc8df0245,c_scale,fl_relative,w_1.0,h_1.0,fl_layer_apply/8e581394-e67c-4f37-bb7a-8fd964775070/WMNS+AIR+JORDAN+MULE.png",
    "color_label": "Dark Team Red/Burgundy Crush/Metallic Silver",
    "original_price": null,
    "current_price": 4900,
    "full_size_list": [
      "CM 22",
      "CM 23",
      "CM 24",
      "CM 25",
      "CM 26",
      "CM 27"
    ],
    "available_list": [
      "CM 23",
      "CM 24",
      "CM 25",
      "CM 26",
      "CM 27"
    ]
  },
  {
    "sku_id": "nike-HV8288-100-Sail/Coconut_Milk/Anthracite",
    "brand": "NIKE",
    "parent_id": "HV8288-100",
    "sku_url": "https://www.nike.com/tw/t/air-jordan-1-triple-stack-pahhHbBT/HV8288-100",
    "category": "woman_shoes",
    "product_name": "Air Jordan 1 Triple Stack",
    "img_path": "https://static.nike.com/a/images/t_default/u_126ab356-44d8-4a06-89b4-fcdcc8df0245,c_scale,fl_relative,w_1.0,h_1.0,fl_layer_apply/9a004ca6-d3d7-44e8-b7b2-908e1a186eaf/WMNS+AIR+JORDAN+1+TRIPLE+STACK.png",
    "color_label": "Sail/Coconut Milk/Anthracite",
    "original_price": null,
    "current_price": 4500,
    "full_size_list": [
      "CM 22",
      "CM 22.5",
      "CM 23",
      "CM 23.5",
      "CM 24",
      "CM 24.5",
      "CM 25",
      "CM 25.5",
      "CM 26",
      "CM 26.5",
      "CM 27"
    ],
    "available_list": [
      "CM 24",
      "CM 24.5",
      "CM 25",
      "CM 25.5",
      "CM 26"
    ]
  },
  {
    "sku_id": "nike-HV8288-600-Team_Red/Pale_Ivory/Sanded_Gold",
    "brand": "NIKE",
    "parent_id": "HV8288-600",
    "sku_url": "https://www.nike.com/tw/t/air-jordan-1-triple-stack-pahhHbBT/HV8288-600",
    "category": "woman_shoes",
    "product_name": "Air Jordan 1 Triple Stack",
    "img_path": "https://static.nike.com/a/images/t_default/u_126ab356-44d8-4a06-89b4-fcdcc8df0245,c_scale,fl_relative,w_1.0,h_1.0,fl_layer_apply/a2d279de-139f-467f-a063-025ae337e83b/WMNS+AIR+JORDAN+1+TRIPLE+STACK.png",
    "color_label": "Team Red/Pale Ivory/Sanded Gold",
    "original_price": null,
    "current_price": 4500,
    "full_size_list": [
      "CM 22.5",
      "CM 23",
      "CM 23.5",
      "CM 24",
      "CM 24.5",
      "CM 25",
      "CM 25.5",
      "CM 26",
      "CM 26.5"
    ],
    "available_list": [
      "CM 23",
      "CM 23.5",
      "CM 24",
      "CM 24.5",
      "CM 25",
      "CM 25.5",
      "CM 26",
      "CM 26.5"
    ]
  },
  {
    "sku_id": "nike-HV8288-402-Psychic_Blue/白色/Sail/Psychic_Blue",
    "brand": "NIKE",
    "parent_id": "HV8288-402",
    "sku_url": "https://www.nike.com/tw/t/air-jordan-1-triple-stack-pahhHbBT/HV8288-402",
    "category": "woman_shoes",
    "product_name": "Air Jordan 1 Triple Stack",
    "img_path": "https://static.nike.com/a/images/t_default/u_126ab356-44d8-4a06-89b4-fcdcc8df0245,c_scale,fl_relative,w_1.0,h_1.0,fl_layer_apply/7bbca7c9-5a6e-42e5-a6fc-72a829050824/WMNS+AIR+JORDAN+1+TRIPLE+STACK.png",
    "color_label": "Psychic Blue/白色/Sail/Psychic Blue",
    "original_price": null,
    "current_price": 4500,
    "full_size_list": [
      "CM 22.5",
      "CM 23",
      "CM 23.5",
      "CM 24",
      "CM 24.5",
      "CM 25",
      "CM 25.5",
      "CM 26",
      "CM 26.5"
    ],
    "available_list": [
      "CM 23",
      "CM 23.5",
      "CM 24",
      "CM 24.5",
      "CM 25",
      "CM 25.5",
      "CM 26",
      "CM 26.5"
    ]
  },
  {
    "sku_id": "nike-IB7007-107-Pale_Ivory/黑色/Muslin/Racer_Pink",
    "brand": "NIKE",
    "parent_id": "IB7007-107",
    "sku_url": "https://www.nike.com/tw/t/air-jordan-1-%E4%B8%AD%E7%AD%92-se-edge-u8YpWQGc/IB7007-107",
    "category": "woman_shoes",
    "product_name": "Air Jordan 1 中筒 SE Edge",
    "img_path": "https://static.nike.com/a/images/t_default/u_126ab356-44d8-4a06-89b4-fcdcc8df0245,c_scale,fl_relative,w_1.0,h_1.0,fl_layer_apply/025e7260-f757-4b85-b1f8-267840725bd3/WMNS+AIR+JORDAN+1+MID+SE+EDG.png",
    "color_label": "Pale Ivory/黑色/Muslin/Racer Pink",
    "original_price": null,
    "current_price": 4500,
    "full_size_list": [
      "CM 22",
      "CM 22.5",
      "CM 23",
      "CM 23.5",
      "CM 24",
      "CM 24.5",
      "CM 25",
      "CM 25.5",
      "CM 26",
      "CM 26.5",
      "CM 27"
    ],
    "available_list": [
      "CM 22",
      "CM 22.5",
      "CM 23",
      "CM 23.5",
      "CM 24",
      "CM 24.5",
      "CM 25",
      "CM 25.5",
      "CM 26",
      "CM 26.5"
    ]
  },
  {
    "sku_id": "nike-HF2882-100-Summit_White/Photon_Dust/Washed_Coral/Iron_Grey",
    "brand": "NIKE",
    "parent_id": "HF2882-100",
    "sku_url": "https://www.nike.com/tw/t/sabrina-3-ep-%E7%B1%83%E7%90%83-G2lc4oD7/HF2882-100",
    "category": "woman_shoes",
    "product_name": "Sabrina 3 \"Silencer\" EP",
    "img_path": "https://static.nike.com/a/images/t_default/u_9ddf04c7-2a9a-4d76-add1-d15af8f0263d,c_scale,fl_relative,w_1.0,h_1.0,fl_layer_apply/f6d256b4-dd65-49d1-8375-e72d6e0fbe6b/SABRINA+3+EP.png",
    "color_label": "Summit White/Photon Dust/Washed Coral/Iron Grey",
    "original_price": null,
    "current_price": 3655,
    "full_size_list": [
      "CM 22",
      "CM 22.5",
      "CM 23",
      "CM 23.5",
      "CM 24",
      "CM 24.5",
      "CM 25",
      "CM 25.5",
      "CM 26",
      "CM 26.5",
      "CM 27",
      "CM 27.5",
      "CM 28",
      "CM 28.5",
      "CM 29",
      "CM 29.5",
      "CM 30",
      "CM 30.5",
      "CM 31",
      "CM 31.5",
      "CM 32.5",
      "CM 33.5"
    ],
    "available_list": [
      "CM 22",
      "CM 30.5"
    ]
  },
  {
    "sku_id": "nike-HF2882-101-白色/Mint_Foam/Metallic_Silver",
    "brand": "NIKE",
    "parent_id": "HF2882-101",
    "sku_url": "https://www.nike.com/tw/t/sabrina-3-ep-%E7%B1%83%E7%90%83-G2lc4oD7/HF2882-101",
    "category": "woman_shoes",
    "product_name": "Sabrina 3 EP",
    "img_path": "https://static.nike.com/a/images/t_default/u_9ddf04c7-2a9a-4d76-add1-d15af8f0263d,c_scale,fl_relative,w_1.0,h_1.0,fl_layer_apply/bcce47be-9654-41f3-a63f-331602bc3486/SABRINA+3+EP.png",
    "color_label": "白色/Mint Foam/Metallic Silver",
    "original_price": null,
    "current_price": 3870,
    "full_size_list": [
      "CM 22",
      "CM 22.5",
      "CM 23",
      "CM 23.5",
      "CM 24",
      "CM 24.5",
      "CM 25",
      "CM 25.5",
      "CM 26",
      "CM 26.5",
      "CM 27",
      "CM 27.5",
      "CM 28",
      "CM 28.5",
      "CM 29",
      "CM 29.5",
      "CM 30",
      "CM 30.5",
      "CM 31"
    ],
    "available_list": [
      "CM 22",
      "CM 22.5",
      "CM 23",
      "CM 23.5",
      "CM 24",
      "CM 24.5",
      "CM 25",
      "CM 25.5",
      "CM 26",
      "CM 26.5",
      "CM 27",
      "CM 27.5",
      "CM 28.5",
      "CM 29.5",
      "CM 30.5",
      "CM 31"
    ]
  },
  {
    "sku_id": "nike-HF2882-800-Crimson_Tint/Arctic_Punch/Light_Current_Blue/黑色",
    "brand": "NIKE",
    "parent_id": "HF2882-800",
    "sku_url": "https://www.nike.com/tw/t/sabrina-3-ep-%E7%B1%83%E7%90%83-G2lc4oD7/HF2882-800",
    "category": "woman_shoes",
    "product_name": "Sabrina 3 EP",
    "img_path": "https://static.nike.com/a/images/t_default/u_9ddf04c7-2a9a-4d76-add1-d15af8f0263d,c_scale,fl_relative,w_1.0,h_1.0,fl_layer_apply/7c7d0fa2-b6c4-4c14-9b77-464760b014f2/SABRINA+3+EP.png",
    "color_label": "Crimson Tint/Arctic Punch/Light Current Blue/黑色",
    "original_price": null,
    "current_price": 4300,
    "full_size_list": [
      "CM 22",
      "CM 22.5",
      "CM 23",
      "CM 23.5",
      "CM 24",
      "CM 24.5",
      "CM 25",
      "CM 25.5",
      "CM 26",
      "CM 26.5",
      "CM 27",
      "CM 27.5",
      "CM 28",
      "CM 28.5",
      "CM 29",
      "CM 29.5",
      "CM 30.5"
    ],
    "available_list": [
      "CM 22",
      "CM 22.5",
      "CM 23",
      "CM 23.5",
      "CM 24",
      "CM 24.5",
      "CM 25",
      "CM 25.5",
      "CM 26",
      "CM 26.5",
      "CM 27",
      "CM 27.5",
      "CM 28",
      "CM 28.5",
      "CM 29",
      "CM 29.5",
      "CM 30.5"
    ]
  },
  {
    "sku_id": "nike-HF2882-400-Glacier_Blue/Light_Armory_Blue/Still_Blue/Metallic_Gold",
    "brand": "NIKE",
    "parent_id": "HF2882-400",
    "sku_url": "https://www.nike.com/tw/t/sabrina-3-ep-%E7%B1%83%E7%90%83-G2lc4oD7/HF2882-400",
    "category": "woman_shoes",
    "product_name": "Sabrina 3 \"Blueprint\" EP",
    "img_path": "https://static.nike.com/a/images/t_default/u_9ddf04c7-2a9a-4d76-add1-d15af8f0263d,c_scale,fl_relative,w_1.0,h_1.0,fl_layer_apply/7225074b-f079-4b33-b2a8-cdd12df52021/SABRINA+3+EP.png",
    "color_label": "Glacier Blue/Light Armory Blue/Still Blue/Metallic Gold",
    "original_price": null,
    "current_price": 3870,
    "full_size_list": [
      "CM 22",
      "CM 22.5",
      "CM 23",
      "CM 23.5",
      "CM 24",
      "CM 24.5",
      "CM 25",
      "CM 25.5",
      "CM 26",
      "CM 26.5",
      "CM 27",
      "CM 27.5",
      "CM 28",
      "CM 28.5",
      "CM 29",
      "CM 29.5",
      "CM 30",
      "CM 30.5",
      "CM 31",
      "CM 31.5",
      "CM 32.5",
      "CM 33.5"
    ],
    "available_list": [
      "CM 23",
      "CM 26",
      "CM 26.5",
      "CM 27",
      "CM 27.5",
      "CM 28",
      "CM 28.5",
      "CM 29",
      "CM 29.5",
      "CM 30.5",
      "CM 31"
    ]
  },
  {
    "sku_id": "nike-HF2882-500-Barely_Grape/Magic_Ember/Bright_Peach/黑色",
    "brand": "NIKE",
    "parent_id": "HF2882-500",
    "sku_url": "https://www.nike.com/tw/t/sabrina-3-ep-%E7%B1%83%E7%90%83-G2lc4oD7/HF2882-500",
    "category": "woman_shoes",
    "product_name": "Sabrina 3 \"Radiant\" EP",
    "img_path": "https://static.nike.com/a/images/t_default/u_9ddf04c7-2a9a-4d76-add1-d15af8f0263d,c_scale,fl_relative,w_1.0,h_1.0,fl_layer_apply/12773e65-3c79-445a-9a13-592b0f6f1ca4/SABRINA+3+EP.png",
    "color_label": "Barely Grape/Magic Ember/Bright Peach/黑色",
    "original_price": null,
    "current_price": 3870,
    "full_size_list": [
      "CM 22",
      "CM 22.5",
      "CM 23",
      "CM 23.5",
      "CM 24",
      "CM 24.5",
      "CM 25",
      "CM 25.5",
      "CM 26",
      "CM 26.5",
      "CM 27",
      "CM 27.5",
      "CM 28",
      "CM 28.5",
      "CM 29",
      "CM 29.5",
      "CM 30",
      "CM 30.5",
      "CM 31",
      "CM 31.5",
      "CM 32",
      "CM 32.5",
      "CM 33.5"
    ],
    "available_list": [
      "CM 22",
      "CM 22.5",
      "CM 23",
      "CM 23.5",
      "CM 24",
      "CM 24.5",
      "CM 25",
      "CM 25.5",
      "CM 26",
      "CM 26.5",
      "CM 27",
      "CM 27.5",
      "CM 28",
      "CM 28.5",
      "CM 29",
      "CM 29.5",
      "CM 30",
      "CM 30.5",
      "CM 31"
    ]
  },
  {
    "sku_id": "nike-HF2882-001-黑色/Dark_Smoke_Grey/Iron_Grey/白色",
    "brand": "NIKE",
    "parent_id": "HF2882-001",
    "sku_url": "https://www.nike.com/tw/t/sabrina-3-ep-%E7%B1%83%E7%90%83-G2lc4oD7/HF2882-001",
    "category": "woman_shoes",
    "product_name": "Sabrina 3 EP",
    "img_path": "https://static.nike.com/a/images/t_default/u_9ddf04c7-2a9a-4d76-add1-d15af8f0263d,c_scale,fl_relative,w_1.0,h_1.0,fl_layer_apply/a599a446-9313-47df-b88f-af02aa426118/SABRINA+3+EP.png",
    "color_label": "黑色/Dark Smoke Grey/Iron Grey/白色",
    "original_price": null,
    "current_price": 4300,
    "full_size_list": [
      "CM 22",
      "CM 22.5",
      "CM 23",
      "CM 23.5",
      "CM 24",
      "CM 24.5",
      "CM 25",
      "CM 25.5",
      "CM 26",
      "CM 26.5",
      "CM 27",
      "CM 27.5",
      "CM 28",
      "CM 28.5",
      "CM 29",
      "CM 29.5",
      "CM 30.5"
    ],
    "available_list": [
      "CM 22",
      "CM 22.5",
      "CM 23",
      "CM 23.5",
      "CM 24",
      "CM 24.5",
      "CM 25",
      "CM 25.5",
      "CM 26",
      "CM 26.5",
      "CM 27",
      "CM 27.5",
      "CM 28",
      "CM 28.5",
      "CM 29",
      "CM 29.5"
    ]
  },
  {
    "sku_id": "nike-HF2882-002-Iron_Grey/Barely_Volt/Mint_Foam/Aluminum",
    "brand": "NIKE",
    "parent_id": "HF2882-002",
    "sku_url": "https://www.nike.com/tw/t/sabrina-3-ep-%E7%B1%83%E7%90%83-G2lc4oD7/HF2882-002",
    "category": "woman_shoes",
    "product_name": "Sabrina 3 EP",
    "img_path": "https://static.nike.com/a/images/t_default/u_9ddf04c7-2a9a-4d76-add1-d15af8f0263d,c_scale,fl_relative,w_1.0,h_1.0,fl_layer_apply/1ae3e7a6-83b9-4ef1-a46a-6de0d93345ec/SABRINA+3+EP.png",
    "color_label": "Iron Grey/Barely Volt/Mint Foam/Aluminum",
    "original_price": null,
    "current_price": 4300,
    "full_size_list": [
      "CM 22",
      "CM 22.5",
      "CM 23",
      "CM 23.5",
      "CM 24",
      "CM 24.5",
      "CM 25",
      "CM 25.5",
      "CM 26",
      "CM 26.5",
      "CM 27",
      "CM 27.5",
      "CM 28",
      "CM 28.5",
      "CM 29",
      "CM 29.5",
      "CM 30",
      "CM 31"
    ],
    "available_list": [
      "CM 22",
      "CM 22.5",
      "CM 23",
      "CM 23.5",
      "CM 24",
      "CM 24.5",
      "CM 25",
      "CM 25.5",
      "CM 26",
      "CM 26.5",
      "CM 27",
      "CM 27.5",
      "CM 28",
      "CM 28.5",
      "CM 29",
      "CM 29.5",
      "CM 30",
      "CM 31"
    ]
  },
  {
    "sku_id": "nike-HF2882-600-Pink_Oxford/Reb_Stardust/Enamel_Green/Coconut_Milk",
    "brand": "NIKE",
    "parent_id": "HF2882-600",
    "sku_url": "https://www.nike.com/tw/t/sabrina-3-ep-%E7%B1%83%E7%90%83-G2lc4oD7/HF2882-600",
    "category": "woman_shoes",
    "product_name": "Sabrina 3 EP",
    "img_path": "https://static.nike.com/a/images/t_default/u_9ddf04c7-2a9a-4d76-add1-d15af8f0263d,c_scale,fl_relative,w_1.0,h_1.0,fl_layer_apply/85c29a62-4b60-4dde-acb8-8ebb1c03bcaf/SABRINA+3+EP.png",
    "color_label": "Pink Oxford/Reb Stardust/Enamel Green/Coconut Milk",
    "original_price": null,
    "current_price": 4300,
    "full_size_list": [
      "CM 22",
      "CM 22.5",
      "CM 23",
      "CM 23.5",
      "CM 24",
      "CM 24.5",
      "CM 25",
      "CM 25.5",
      "CM 26",
      "CM 26.5",
      "CM 27",
      "CM 27.5",
      "CM 28",
      "CM 28.5",
      "CM 29",
      "CM 29.5",
      "CM 30",
      "CM 31"
    ],
    "available_list": [
      "CM 22",
      "CM 22.5",
      "CM 23",
      "CM 23.5",
      "CM 24",
      "CM 24.5",
      "CM 25",
      "CM 25.5",
      "CM 26",
      "CM 26.5",
      "CM 27",
      "CM 27.5",
      "CM 28",
      "CM 28.5",
      "CM 29",
      "CM 29.5",
      "CM 30",
      "CM 31"
    ]
  },
  {
    "sku_id": "nike-HF2882-003-Phantom/Ivory/Rush_Coral/黑色",
    "brand": "NIKE",
    "parent_id": "HF2882-003",
    "sku_url": "https://www.nike.com/tw/t/sabrina-3-ep-%E7%B1%83%E7%90%83-G2lc4oD7/HF2882-003",
    "category": "woman_shoes",
    "product_name": "Sabrina 3 EP",
    "img_path": "https://static.nike.com/a/images/t_default/08e01dcf-c278-4bc8-8242-4f18f23bc2f3/SABRINA+3+EP.png",
    "color_label": "Phantom/Ivory/Rush Coral/黑色",
    "original_price": null,
    "current_price": 4300,
    "full_size_list": [
      "CM 22",
      "CM 22.5",
      "CM 23",
      "CM 23.5",
      "CM 24",
      "CM 24.5",
      "CM 25",
      "CM 25.5",
      "CM 26",
      "CM 26.5",
      "CM 27",
      "CM 27.5",
      "CM 28",
      "CM 28.5",
      "CM 29",
      "CM 29.5",
      "CM 30",
      "CM 31"
    ],
    "available_list": [
      "CM 22",
      "CM 22.5",
      "CM 23",
      "CM 23.5",
      "CM 24",
      "CM 24.5",
      "CM 25",
      "CM 25.5",
      "CM 26",
      "CM 26.5",
      "CM 27",
      "CM 27.5",
      "CM 28",
      "CM 28.5",
      "CM 29",
      "CM 29.5",
      "CM 30",
      "CM 31"
    ]
  },
  {
    "sku_id": "nike-HF2882-301-Clay_Green/Seafoam/Volt_Tint/Sequoia",
    "brand": "NIKE",
    "parent_id": "HF2882-301",
    "sku_url": "https://www.nike.com/tw/t/sabrina-3-ep-%E7%B1%83%E7%90%83-G2lc4oD7/HF2882-301",
    "category": "woman_shoes",
    "product_name": "Sabrina 3 EP",
    "img_path": "https://static.nike.com/a/images/t_default/u_9ddf04c7-2a9a-4d76-add1-d15af8f0263d,c_scale,fl_relative,w_1.0,h_1.0,fl_layer_apply/9d532656-b1dc-4f1e-8f20-07e8c148ca69/SABRINA+3+EP.png",
    "color_label": "Clay Green/Seafoam/Volt Tint/Sequoia",
    "original_price": null,
    "current_price": 4300,
    "full_size_list": [
      "CM 22",
      "CM 22.5",
      "CM 23",
      "CM 23.5",
      "CM 24",
      "CM 24.5",
      "CM 25",
      "CM 25.5",
      "CM 26",
      "CM 26.5",
      "CM 27",
      "CM 27.5",
      "CM 28",
      "CM 28.5",
      "CM 29",
      "CM 29.5",
      "CM 30.5"
    ],
    "available_list": [
      "CM 22",
      "CM 22.5",
      "CM 23",
      "CM 23.5",
      "CM 24",
      "CM 24.5",
      "CM 25",
      "CM 25.5",
      "CM 26",
      "CM 26.5",
      "CM 27",
      "CM 27.5",
      "CM 28",
      "CM 28.5",
      "CM 29",
      "CM 29.5",
      "CM 30.5"
    ]
  },
  {
    "sku_id": "nike-IQ8102-100-Chalk/Pale_Ivory/Summit_White/白色",
    "brand": "NIKE",
    "parent_id": "IQ8102-100",
    "sku_url": "https://www.nike.com/tw/t/vomero-premium-%E8%B7%AF%E8%B7%91-G5MaFK10/IQ8102-100",
    "category": "woman_shoes",
    "product_name": "Nike Vomero Premium",
    "img_path": "https://static.nike.com/a/images/t_default/u_9ddf04c7-2a9a-4d76-add1-d15af8f0263d,c_scale,fl_relative,w_1.0,h_1.0,fl_layer_apply/3fc849e8-4dce-4375-a2f8-ccbf888a16c3/W+NIKE+VOMERO+PREMIUM+ESS.png",
    "color_label": "Chalk/Pale Ivory/Summit White/白色",
    "original_price": null,
    "current_price": 7200,
    "full_size_list": [
      "CM 22",
      "CM 22.5",
      "CM 23",
      "CM 23.5",
      "CM 24",
      "CM 24.5",
      "CM 25",
      "CM 25.5",
      "CM 26",
      "CM 26.5",
      "CM 27"
    ],
    "available_list": [
      "CM 24",
      "CM 25"
    ]
  },
  {
    "sku_id": "nike-FD8315-600-Bright_Crimson/Lime_Blast/Mint_Foam/Cave_Purple",
    "brand": "NIKE",
    "parent_id": "FD8315-600",
    "sku_url": "https://www.nike.com/tw/t/alphafly-3-%E8%B7%AF%E8%B7%91%E7%AB%B6%E9%80%9F-C4VXTw/FD8315-600",
    "category": "woman_shoes",
    "product_name": "Nike Alphafly 3",
    "img_path": "https://static.nike.com/a/images/t_default/u_9ddf04c7-2a9a-4d76-add1-d15af8f0263d,c_scale,fl_relative,w_1.0,h_1.0,fl_layer_apply/1c2b738d-1ab8-4a5e-8f17-a0a4f0bc2072/W+AIR+ZOOM+ALPHAFLY+NEXT%25+3.png",
    "color_label": "Bright Crimson/Lime Blast/Mint Foam/Cave Purple",
    "original_price": null,
    "current_price": 8240,
    "full_size_list": [
      "CM 22",
      "CM 22.5",
      "CM 23",
      "CM 23.5",
      "CM 24",
      "CM 24.5",
      "CM 25",
      "CM 25.5",
      "CM 26",
      "CM 26.5",
      "CM 27"
    ],
    "available_list": [
      "CM 23",
      "CM 23.5",
      "CM 24",
      "CM 24.5",
      "CM 25",
      "CM 25.5",
      "CM 26"
    ]
  },
  {
    "sku_id": "nike-FD8315-101-Coconut_Milk/Dusty_Amethyst/Glacier_Blue/Off_Noir",
    "brand": "NIKE",
    "parent_id": "FD8315-101",
    "sku_url": "https://www.nike.com/tw/t/alphafly-3-%E8%B7%AF%E8%B7%91%E7%AB%B6%E9%80%9F-C4VXTw/FD8315-101",
    "category": "woman_shoes",
    "product_name": "Nike Alphafly 3",
    "img_path": "https://static.nike.com/a/images/t_default/u_9ddf04c7-2a9a-4d76-add1-d15af8f0263d,c_scale,fl_relative,w_1.0,h_1.0,fl_layer_apply/2438e5ee-bf39-406b-9415-425ccaafc515/W+AIR+ZOOM+ALPHAFLY+NEXT%25+3.png",
    "color_label": "Coconut Milk/Dusty Amethyst/Glacier Blue/Off Noir",
    "original_price": null,
    "current_price": 7210,
    "full_size_list": [
      "CM 22",
      "CM 22.5",
      "CM 23",
      "CM 23.5",
      "CM 24",
      "CM 24.5",
      "CM 25",
      "CM 25.5",
      "CM 26",
      "CM 26.5",
      "CM 27",
      "CM 27.5",
      "CM 28"
    ],
    "available_list": [
      "CM 23",
      "CM 23.5",
      "CM 24",
      "CM 24.5",
      "CM 25",
      "CM 25.5"
    ]
  },
  {
    "sku_id": "nike-FD8315-001-Football_Grey/Ghost/Persian_Violet/Blue_Void",
    "brand": "NIKE",
    "parent_id": "FD8315-001",
    "sku_url": "https://www.nike.com/tw/t/alphafly-3-%E8%B7%AF%E8%B7%91%E7%AB%B6%E9%80%9F-C4VXTw/FD8315-001",
    "category": "woman_shoes",
    "product_name": "Nike Alphafly 3",
    "img_path": "https://static.nike.com/a/images/t_default/u_9ddf04c7-2a9a-4d76-add1-d15af8f0263d,c_scale,fl_relative,w_1.0,h_1.0,fl_layer_apply/49cecf57-1f3e-4c43-8685-b7694eed04ff/W+AIR+ZOOM+ALPHAFLY+NEXT%25+3.png",
    "color_label": "Football Grey/Ghost/Persian Violet/Blue Void",
    "original_price": null,
    "current_price": 7210,
    "full_size_list": [
      "CM 22",
      "CM 22.5",
      "CM 23",
      "CM 23.5",
      "CM 24",
      "CM 24.5",
      "CM 25",
      "CM 25.5",
      "CM 26",
      "CM 26.5",
      "CM 27"
    ],
    "available_list": [
      "CM 23",
      "CM 23.5",
      "CM 24",
      "CM 24.5",
      "CM 25"
    ]
  },
  {
    "sku_id": "nike-FD8315-400-Glacier_Blue/Mint_Foam/Green_Shock/黑色",
    "brand": "NIKE",
    "parent_id": "FD8315-400",
    "sku_url": "https://www.nike.com/tw/t/alphafly-3-%E8%B7%AF%E8%B7%91%E7%AB%B6%E9%80%9F-C4VXTw/FD8315-400",
    "category": "woman_shoes",
    "product_name": "Nike Alphafly 3",
    "img_path": "https://static.nike.com/a/images/t_default/u_9ddf04c7-2a9a-4d76-add1-d15af8f0263d,c_scale,fl_relative,w_1.0,h_1.0,fl_layer_apply/689213de-9081-4f27-8a94-74fb3e3d6a78/W+AIR+ZOOM+ALPHAFLY+NEXT%25+3.png",
    "color_label": "Glacier Blue/Mint Foam/Green Shock/黑色",
    "original_price": null,
    "current_price": 10300,
    "full_size_list": [
      "CM 22",
      "CM 22.5",
      "CM 23",
      "CM 23.5",
      "CM 24",
      "CM 24.5",
      "CM 25",
      "CM 25.5",
      "CM 26",
      "CM 26.5",
      "CM 27",
      "CM 27.5",
      "CM 28"
    ],
    "available_list": [
      "CM 22.5",
      "CM 23",
      "CM 23.5",
      "CM 24",
      "CM 24.5",
      "CM 25",
      "CM 25.5",
      "CM 26",
      "CM 26.5",
      "CM 27",
      "CM 27.5"
    ]
  },
  {
    "sku_id": "nike-FD8315-104-白色/Hyper_Turquoise/Concord/黑色",
    "brand": "NIKE",
    "parent_id": "FD8315-104",
    "sku_url": "https://www.nike.com/tw/t/alphafly-3-%E8%B7%AF%E8%B7%91%E7%AB%B6%E9%80%9F-C4VXTw/FD8315-104",
    "category": "woman_shoes",
    "product_name": "Nike Alphafly 3",
    "img_path": "https://static.nike.com/a/images/t_default/u_9ddf04c7-2a9a-4d76-add1-d15af8f0263d,c_scale,fl_relative,w_1.0,h_1.0,fl_layer_apply/9b9b37b8-91a3-412f-8a88-8cc29afb51ee/W+AIR+ZOOM+ALPHAFLY+NEXT%25+3.png",
    "color_label": "白色/Hyper Turquoise/Concord/黑色",
    "original_price": null,
    "current_price": 10300,
    "full_size_list": [
      "CM 22",
      "CM 22.5",
      "CM 23",
      "CM 23.5",
      "CM 24",
      "CM 24.5",
      "CM 25",
      "CM 25.5",
      "CM 26",
      "CM 26.5",
      "CM 27"
    ],
    "available_list": [
      "CM 22",
      "CM 22.5",
      "CM 23",
      "CM 23.5",
      "CM 24",
      "CM 24.5",
      "CM 25",
      "CM 25.5",
      "CM 26",
      "CM 26.5",
      "CM 27"
    ]
  },
  {
    "sku_id": "nike-FD8315-601-Hyper_Pink/Crimson_Tint/Pink_Spell/Bordeaux",
    "brand": "NIKE",
    "parent_id": "FD8315-601",
    "sku_url": "https://www.nike.com/tw/t/alphafly-3-%E8%B7%AF%E8%B7%91%E7%AB%B6%E9%80%9F-C4VXTw/FD8315-601",
    "category": "woman_shoes",
    "product_name": "Nike Alphafly 3",
    "img_path": "https://static.nike.com/a/images/t_default/u_9ddf04c7-2a9a-4d76-add1-d15af8f0263d,c_scale,fl_relative,w_1.0,h_1.0,fl_layer_apply/5cb0535c-ce52-45c3-bde1-8dad17e5022c/W+AIR+ZOOM+ALPHAFLY+NEXT%25+3.png",
    "color_label": "Hyper Pink/Crimson Tint/Pink Spell/Bordeaux",
    "original_price": null,
    "current_price": 9270,
    "full_size_list": [
      "CM 22",
      "CM 22.5",
      "CM 23",
      "CM 23.5",
      "CM 24",
      "CM 24.5",
      "CM 25",
      "CM 25.5",
      "CM 26",
      "CM 26.5",
      "CM 27"
    ],
    "available_list": [
      "CM 22",
      "CM 22.5",
      "CM 23",
      "CM 23.5",
      "CM 24",
      "CM 24.5",
      "CM 25",
      "CM 25.5",
      "CM 26",
      "CM 26.5"
    ]
  },
  {
    "sku_id": "nike-FD8315-500-Fuchsia_Glow/Bright_Violet/Sapphire/Purple_Dynasty",
    "brand": "NIKE",
    "parent_id": "FD8315-500",
    "sku_url": "https://www.nike.com/tw/t/alphafly-3-%E8%B7%AF%E8%B7%91%E7%AB%B6%E9%80%9F-C4VXTw/FD8315-500",
    "category": "woman_shoes",
    "product_name": "Nike Alphafly 3",
    "img_path": "https://static.nike.com/a/images/t_default/u_9ddf04c7-2a9a-4d76-add1-d15af8f0263d,c_scale,fl_relative,w_1.0,h_1.0,fl_layer_apply/fa144942-5012-4014-8afb-bee5bb15481a/W+AIR+ZOOM+ALPHAFLY+NEXT%25+3.png",
    "color_label": "Fuchsia Glow/Bright Violet/Sapphire/Purple Dynasty",
    "original_price": null,
    "current_price": 10300,
    "full_size_list": [
      "CM 22",
      "CM 22.5",
      "CM 23",
      "CM 23.5",
      "CM 24",
      "CM 24.5",
      "CM 25",
      "CM 25.5",
      "CM 26",
      "CM 26.5",
      "CM 27"
    ],
    "available_list": [
      "CM 22",
      "CM 22.5",
      "CM 23",
      "CM 23.5",
      "CM 24",
      "CM 24.5",
      "CM 25",
      "CM 25.5",
      "CM 26",
      "CM 26.5",
      "CM 27"
    ]
  },
  {
    "sku_id": "nike-FD8315-800-Laser_Orange/Citron_Pulse/Volt_Ice/Indigo_Burst",
    "brand": "NIKE",
    "parent_id": "FD8315-800",
    "sku_url": "https://www.nike.com/tw/t/alphafly-3-%E8%B7%AF%E8%B7%91%E7%AB%B6%E9%80%9F-C4VXTw/FD8315-800",
    "category": "woman_shoes",
    "product_name": "Nike Alphafly 3",
    "img_path": "https://static.nike.com/a/images/t_default/u_9ddf04c7-2a9a-4d76-add1-d15af8f0263d,c_scale,fl_relative,w_1.0,h_1.0,fl_layer_apply/3472880f-0c98-4352-b525-96ae70ca71f9/W+AIR+ZOOM+ALPHAFLY+NEXT%25+3.png",
    "color_label": "Laser Orange/Citron Pulse/Volt Ice/Indigo Burst",
    "original_price": null,
    "current_price": 10300,
    "full_size_list": [
      "CM 22",
      "CM 22.5",
      "CM 23",
      "CM 23.5",
      "CM 24",
      "CM 24.5",
      "CM 25",
      "CM 25.5",
      "CM 26",
      "CM 26.5",
      "CM 27"
    ],
    "available_list": [
      "CM 22",
      "CM 22.5",
      "CM 23",
      "CM 23.5",
      "CM 24",
      "CM 24.5",
      "CM 25",
      "CM 25.5",
      "CM 26",
      "CM 26.5",
      "CM 27"
    ]
  },
  {
    "sku_id": "nike-IO1259-002-Grey_Fog/Metallic_Silver/Grey_Fog",
    "brand": "NIKE",
    "parent_id": "IO1259-002",
    "sku_url": "https://www.nike.com/tw/t/air-force-1-07-premium-6dqQcsEQ/IO1259-002",
    "category": "woman_shoes",
    "product_name": "Nike Air Force 1 '07 Premium+",
    "img_path": "https://static.nike.com/a/images/t_default/u_9ddf04c7-2a9a-4d76-add1-d15af8f0263d,c_scale,fl_relative,w_1.0,h_1.0,fl_layer_apply/a93d9f1e-01cd-4c33-bf0c-b4cb6a26c20f/W+AIR+FORCE+1+%2707+PRM%2B.png",
    "color_label": "Grey Fog/Metallic Silver/Grey Fog",
    "original_price": null,
    "current_price": 4000,
    "full_size_list": [
      "CM 22",
      "CM 22.5",
      "CM 23",
      "CM 23.5",
      "CM 24",
      "CM 24.5",
      "CM 25",
      "CM 25.5",
      "CM 26",
      "CM 26.5",
      "CM 27"
    ],
    "available_list": [
      "CM 22",
      "CM 22.5",
      "CM 23",
      "CM 23.5",
      "CM 24",
      "CM 24.5",
      "CM 25",
      "CM 25.5",
      "CM 26",
      "CM 26.5",
      "CM 27"
    ]
  },
  {
    "sku_id": "nike-IO1259-001-黑色/Metallic_Gold/黑色",
    "brand": "NIKE",
    "parent_id": "IO1259-001",
    "sku_url": "https://www.nike.com/tw/t/air-force-1-07-premium-6dqQcsEQ/IO1259-001",
    "category": "woman_shoes",
    "product_name": "Nike Air Force 1 '07 Premium+",
    "img_path": "https://static.nike.com/a/images/t_default/u_9ddf04c7-2a9a-4d76-add1-d15af8f0263d,c_scale,fl_relative,w_1.0,h_1.0,fl_layer_apply/bf93e31a-1bd0-4566-aaa8-c5d1377d842a/W+AIR+FORCE+1+%2707+PRM%2B.png",
    "color_label": "黑色/Metallic Gold/黑色",
    "original_price": null,
    "current_price": 4000,
    "full_size_list": [
      "CM 22",
      "CM 22.5",
      "CM 23",
      "CM 23.5",
      "CM 24",
      "CM 24.5",
      "CM 25",
      "CM 25.5",
      "CM 26",
      "CM 26.5",
      "CM 27"
    ],
    "available_list": [
      "CM 22",
      "CM 22.5",
      "CM 23",
      "CM 23.5",
      "CM 24",
      "CM 24.5",
      "CM 25",
      "CM 25.5",
      "CM 26",
      "CM 26.5",
      "CM 27"
    ]
  },
  {
    "sku_id": "nike-HV8288-100-Sail/Coconut_Milk/Anthracite",
    "brand": "NIKE",
    "parent_id": "HV8288-100",
    "sku_url": "https://www.nike.com/tw/t/air-jordan-1-triple-stack-pahhHbBT/HV8288-100",
    "category": "woman_shoes",
    "product_name": "Air Jordan 1 Triple Stack",
    "img_path": "https://static.nike.com/a/images/t_default/u_126ab356-44d8-4a06-89b4-fcdcc8df0245,c_scale,fl_relative,w_1.0,h_1.0,fl_layer_apply/9a004ca6-d3d7-44e8-b7b2-908e1a186eaf/WMNS+AIR+JORDAN+1+TRIPLE+STACK.png",
    "color_label": "Sail/Coconut Milk/Anthracite",
    "original_price": null,
    "current_price": 4500,
    "full_size_list": [
      "CM 22",
      "CM 22.5",
      "CM 23",
      "CM 23.5",
      "CM 24",
      "CM 24.5",
      "CM 25",
      "CM 25.5",
      "CM 26",
      "CM 26.5",
      "CM 27"
    ],
    "available_list": [
      "CM 24",
      "CM 24.5",
      "CM 25",
      "CM 25.5",
      "CM 26"
    ]
  },
  {
    "sku_id": "nike-HV8288-600-Team_Red/Pale_Ivory/Sanded_Gold",
    "brand": "NIKE",
    "parent_id": "HV8288-600",
    "sku_url": "https://www.nike.com/tw/t/air-jordan-1-triple-stack-pahhHbBT/HV8288-600",
    "category": "woman_shoes",
    "product_name": "Air Jordan 1 Triple Stack",
    "img_path": "https://static.nike.com/a/images/t_default/u_126ab356-44d8-4a06-89b4-fcdcc8df0245,c_scale,fl_relative,w_1.0,h_1.0,fl_layer_apply/a2d279de-139f-467f-a063-025ae337e83b/WMNS+AIR+JORDAN+1+TRIPLE+STACK.png",
    "color_label": "Team Red/Pale Ivory/Sanded Gold",
    "original_price": null,
    "current_price": 4500,
    "full_size_list": [
      "CM 22.5",
      "CM 23",
      "CM 23.5",
      "CM 24",
      "CM 24.5",
      "CM 25",
      "CM 25.5",
      "CM 26",
      "CM 26.5"
    ],
    "available_list": [
      "CM 23",
      "CM 23.5",
      "CM 24",
      "CM 24.5",
      "CM 25",
      "CM 25.5",
      "CM 26",
      "CM 26.5"
    ]
  },
  {
    "sku_id": "nike-HV8288-402-Psychic_Blue/白色/Sail/Psychic_Blue",
    "brand": "NIKE",
    "parent_id": "HV8288-402",
    "sku_url": "https://www.nike.com/tw/t/air-jordan-1-triple-stack-pahhHbBT/HV8288-402",
    "category": "woman_shoes",
    "product_name": "Air Jordan 1 Triple Stack",
    "img_path": "https://static.nike.com/a/images/t_default/u_126ab356-44d8-4a06-89b4-fcdcc8df0245,c_scale,fl_relative,w_1.0,h_1.0,fl_layer_apply/7bbca7c9-5a6e-42e5-a6fc-72a829050824/WMNS+AIR+JORDAN+1+TRIPLE+STACK.png",
    "color_label": "Psychic Blue/白色/Sail/Psychic Blue",
    "original_price": null,
    "current_price": 4500,
    "full_size_list": [
      "CM 22.5",
      "CM 23",
      "CM 23.5",
      "CM 24",
      "CM 24.5",
      "CM 25",
      "CM 25.5",
      "CM 26",
      "CM 26.5"
    ],
    "available_list": [
      "CM 23",
      "CM 23.5",
      "CM 24",
      "CM 24.5",
      "CM 25",
      "CM 25.5",
      "CM 26",
      "CM 26.5"
    ]
  },
  {
    "sku_id": "nike-IH0388-200-Mink_Brown/Light_Bone/College_Grey/Mink_Brown",
    "brand": "NIKE",
    "parent_id": "IH0388-200",
    "sku_url": "https://www.nike.com/tw/t/v2k-run-43YfLxpv/IH0388-200",
    "category": "woman_shoes",
    "product_name": "Nike V2K Run",
    "img_path": "https://static.nike.com/a/images/t_default/u_9ddf04c7-2a9a-4d76-add1-d15af8f0263d,c_scale,fl_relative,w_1.0,h_1.0,fl_layer_apply/9e9ce246-bbe7-475f-b3de-c84199d1d905/W+NIKE+V2K+RUN.png",
    "color_label": "Mink Brown/Light Bone/College Grey/Mink Brown",
    "original_price": null,
    "current_price": 4000,
    "full_size_list": [
      "CM 22",
      "CM 22.5",
      "CM 23",
      "CM 23.5",
      "CM 24",
      "CM 24.5",
      "CM 25",
      "CM 25.5",
      "CM 26",
      "CM 26.5",
      "CM 27"
    ],
    "available_list": [
      "CM 22",
      "CM 22.5",
      "CM 23",
      "CM 23.5",
      "CM 24",
      "CM 24.5",
      "CM 25",
      "CM 25.5",
      "CM 26",
      "CM 26.5"
    ]
  },
  {
    "sku_id": "nike-IH0388-001-黑色/Metallic_Silver/Anthracite/黑色",
    "brand": "NIKE",
    "parent_id": "IH0388-001",
    "sku_url": "https://www.nike.com/tw/t/v2k-run-43YfLxpv/IH0388-001",
    "category": "woman_shoes",
    "product_name": "Nike V2K Run",
    "img_path": "https://static.nike.com/a/images/t_default/u_9ddf04c7-2a9a-4d76-add1-d15af8f0263d,c_scale,fl_relative,w_1.0,h_1.0,fl_layer_apply/6bdcec5b-396c-4e6e-a96c-617206e53eca/W+NIKE+V2K+RUN.png",
    "color_label": "黑色/Metallic Silver/Anthracite/黑色",
    "original_price": null,
    "current_price": 4000,
    "full_size_list": [
      "CM 22",
      "CM 22.5",
      "CM 23",
      "CM 23.5",
      "CM 24",
      "CM 24.5",
      "CM 25",
      "CM 25.5",
      "CM 26",
      "CM 26.5",
      "CM 27"
    ],
    "available_list": [
      "CM 22",
      "CM 22.5",
      "CM 23",
      "CM 23.5",
      "CM 24",
      "CM 24.5",
      "CM 25",
      "CM 25.5",
      "CM 26",
      "CM 26.5",
      "CM 27"
    ]
  },
  {
    "sku_id": "nike-IH0388-002-Cool_Grey/Wolf_Grey/Photon_Dust/Metallic_Silver",
    "brand": "NIKE",
    "parent_id": "IH0388-002",
    "sku_url": "https://www.nike.com/tw/t/v2k-run-43YfLxpv/IH0388-002",
    "category": "woman_shoes",
    "product_name": "Nike V2K Run",
    "img_path": "https://static.nike.com/a/images/t_default/u_9ddf04c7-2a9a-4d76-add1-d15af8f0263d,c_scale,fl_relative,w_1.0,h_1.0,fl_layer_apply/84e11791-a94d-4aa8-b28a-0073d42f62e8/W+NIKE+V2K+RUN.png",
    "color_label": "Cool Grey/Wolf Grey/Photon Dust/Metallic Silver",
    "original_price": null,
    "current_price": 4000,
    "full_size_list": [
      "CM 22",
      "CM 22.5",
      "CM 23",
      "CM 23.5",
      "CM 24",
      "CM 24.5",
      "CM 25",
      "CM 25.5",
      "CM 26",
      "CM 26.5",
      "CM 27"
    ],
    "available_list": [
      "CM 22",
      "CM 22.5",
      "CM 23",
      "CM 23.5",
      "CM 24",
      "CM 24.5",
      "CM 25",
      "CM 25.5",
      "CM 26",
      "CM 26.5",
      "CM 27"
    ]
  },
  {
    "sku_id": "nike-HQ7540-003-黑色/University_Red/黑色",
    "brand": "NIKE",
    "parent_id": "HQ7540-003",
    "sku_url": "https://www.nike.com/tw/t/shox-z-5AFJMyDk/HQ7540-003",
    "category": "woman_shoes",
    "product_name": "Nike Shox Z",
    "img_path": "https://static.nike.com/a/images/t_default/u_9ddf04c7-2a9a-4d76-add1-d15af8f0263d,c_scale,fl_relative,w_1.0,h_1.0,fl_layer_apply/596570e3-af7a-4562-9375-b3bc1555f592/W+NIKE+SHOX+Z.png",
    "color_label": "黑色/University Red/黑色",
    "original_price": null,
    "current_price": 4500,
    "full_size_list": [
      "CM 22",
      "CM 22.5",
      "CM 23",
      "CM 23.5",
      "CM 24",
      "CM 24.5",
      "CM 25",
      "CM 25.5",
      "CM 26",
      "CM 26.5",
      "CM 27"
    ],
    "available_list": [
      "CM 22",
      "CM 22.5",
      "CM 23",
      "CM 23.5",
      "CM 24",
      "CM 24.5",
      "CM 25",
      "CM 25.5",
      "CM 26",
      "CM 26.5",
      "CM 27"
    ]
  },
  {
    "sku_id": "nike-HQ7540-002-黑色/University_Red/黑色",
    "brand": "NIKE",
    "parent_id": "HQ7540-002",
    "sku_url": "https://www.nike.com/tw/t/shox-z-5AFJMyDk/HQ7540-002",
    "category": "woman_shoes",
    "product_name": "Nike Shox Z",
    "img_path": "https://static.nike.com/a/images/t_default/u_9ddf04c7-2a9a-4d76-add1-d15af8f0263d,c_scale,fl_relative,w_1.0,h_1.0,fl_layer_apply/7eb2b026-28b3-44d1-841b-a07e1f69bdbd/W+NIKE+SHOX+Z.png",
    "color_label": "黑色/University Red/黑色",
    "original_price": null,
    "current_price": 4500,
    "full_size_list": [
      "CM 22",
      "CM 22.5",
      "CM 23",
      "CM 23.5",
      "CM 24",
      "CM 24.5",
      "CM 25",
      "CM 25.5",
      "CM 26",
      "CM 26.5",
      "CM 27"
    ],
    "available_list": [
      "CM 22",
      "CM 22.5",
      "CM 23",
      "CM 23.5",
      "CM 24",
      "CM 24.5",
      "CM 25",
      "CM 25.5",
      "CM 26",
      "CM 26.5",
      "CM 27"
    ]
  },
  {
    "sku_id": "nike-HQ7540-600-Dark_Team_Red/黑色/Mystic_Dates",
    "brand": "NIKE",
    "parent_id": "HQ7540-600",
    "sku_url": "https://www.nike.com/tw/t/shox-z-5AFJMyDk/HQ7540-600",
    "category": "woman_shoes",
    "product_name": "Nike Shox Z",
    "img_path": "https://static.nike.com/a/images/t_default/u_9ddf04c7-2a9a-4d76-add1-d15af8f0263d,c_scale,fl_relative,w_1.0,h_1.0,fl_layer_apply/816c1f79-83d0-42e9-a09d-b982c435a39a/W+NIKE+SHOX+Z.png",
    "color_label": "Dark Team Red/黑色/Mystic Dates",
    "original_price": null,
    "current_price": 4050,
    "full_size_list": [
      "CM 22",
      "CM 22.5",
      "CM 23",
      "CM 23.5",
      "CM 24",
      "CM 24.5",
      "CM 25",
      "CM 25.5",
      "CM 26",
      "CM 26.5",
      "CM 27"
    ],
    "available_list": [
      "CM 22",
      "CM 22.5",
      "CM 23",
      "CM 23.5",
      "CM 24",
      "CM 24.5",
      "CM 25",
      "CM 25.5",
      "CM 26",
      "CM 26.5",
      "CM 27"
    ]
  },
  {
    "sku_id": "nike-HQ7540-601-Pinksicle/黑色",
    "brand": "NIKE",
    "parent_id": "HQ7540-601",
    "sku_url": "https://www.nike.com/tw/t/shox-z-5AFJMyDk/HQ7540-601",
    "category": "woman_shoes",
    "product_name": "Nike Shox Z",
    "img_path": "https://static.nike.com/a/images/t_default/u_9ddf04c7-2a9a-4d76-add1-d15af8f0263d,c_scale,fl_relative,w_1.0,h_1.0,fl_layer_apply/8c74e334-b772-4f60-a2ac-81a1a7b977ed/W+NIKE+SHOX+Z.png",
    "color_label": "Pinksicle/黑色",
    "original_price": null,
    "current_price": 4500,
    "full_size_list": [
      "CM 22",
      "CM 22.5",
      "CM 23",
      "CM 23.5",
      "CM 24",
      "CM 24.5",
      "CM 25",
      "CM 25.5",
      "CM 26",
      "CM 26.5",
      "CM 27"
    ],
    "available_list": [
      "CM 22",
      "CM 22.5",
      "CM 23",
      "CM 23.5",
      "CM 24",
      "CM 24.5",
      "CM 25",
      "CM 25.5",
      "CM 26",
      "CM 26.5",
      "CM 27"
    ]
  },
  {
    "sku_id": "nike-HQ7540-005-黑色/Blue_Hero/Off_Noir",
    "brand": "NIKE",
    "parent_id": "HQ7540-005",
    "sku_url": "https://www.nike.com/tw/t/shox-z-5AFJMyDk/HQ7540-005",
    "category": "woman_shoes",
    "product_name": "Nike Shox Z",
    "img_path": "https://static.nike.com/a/images/t_default/u_9ddf04c7-2a9a-4d76-add1-d15af8f0263d,c_scale,fl_relative,w_1.0,h_1.0,fl_layer_apply/f47c6034-473b-4f68-a22a-6819804a8d4a/W+NIKE+SHOX+Z.png",
    "color_label": "黑色/Blue Hero/Off Noir",
    "original_price": null,
    "current_price": 4500,
    "full_size_list": [
      "CM 22",
      "CM 22.5",
      "CM 23",
      "CM 23.5",
      "CM 24",
      "CM 24.5",
      "CM 25",
      "CM 25.5",
      "CM 26",
      "CM 26.5",
      "CM 27"
    ],
    "available_list": [
      "CM 22",
      "CM 22.5",
      "CM 23",
      "CM 23.5",
      "CM 24",
      "CM 24.5",
      "CM 25",
      "CM 25.5",
      "CM 26",
      "CM 26.5",
      "CM 27"
    ]
  },
  {
    "sku_id": "nike-HQ7540-500-Tattoo/黑色/黑色",
    "brand": "NIKE",
    "parent_id": "HQ7540-500",
    "sku_url": "https://www.nike.com/tw/t/shox-z-5AFJMyDk/HQ7540-500",
    "category": "woman_shoes",
    "product_name": "Nike Shox Z",
    "img_path": "https://static.nike.com/a/images/t_default/u_9ddf04c7-2a9a-4d76-add1-d15af8f0263d,c_scale,fl_relative,w_1.0,h_1.0,fl_layer_apply/5d934fc5-aa95-45a0-a815-625f9ab0ca26/W+NIKE+SHOX+Z.png",
    "color_label": "Tattoo/黑色/黑色",
    "original_price": null,
    "current_price": 4500,
    "full_size_list": [
      "CM 22",
      "CM 22.5",
      "CM 23",
      "CM 23.5",
      "CM 24",
      "CM 24.5",
      "CM 25",
      "CM 25.5",
      "CM 26",
      "CM 26.5",
      "CM 27",
      "CM 27.5"
    ],
    "available_list": [
      "CM 22",
      "CM 22.5",
      "CM 23",
      "CM 23.5",
      "CM 24",
      "CM 24.5",
      "CM 25",
      "CM 25.5",
      "CM 26",
      "CM 26.5",
      "CM 27"
    ]
  },
  {
    "sku_id": "nike-HQ7540-101-白色/Light_Magenta",
    "brand": "NIKE",
    "parent_id": "HQ7540-101",
    "sku_url": "https://www.nike.com/tw/t/shox-z-5AFJMyDk/HQ7540-101",
    "category": "woman_shoes",
    "product_name": "Nike Shox Z",
    "img_path": "https://static.nike.com/a/images/t_default/u_9ddf04c7-2a9a-4d76-add1-d15af8f0263d,c_scale,fl_relative,w_1.0,h_1.0,fl_layer_apply/69752aff-6d07-44ce-8ddc-b9c7aafce7c1/W+NIKE+SHOX+Z.png",
    "color_label": "白色/Light Magenta",
    "original_price": null,
    "current_price": 4500,
    "full_size_list": [
      "CM 22",
      "CM 22.5",
      "CM 23",
      "CM 23.5",
      "CM 24",
      "CM 24.5",
      "CM 25",
      "CM 25.5",
      "CM 26",
      "CM 26.5",
      "CM 27",
      "CM 27.5"
    ],
    "available_list": [
      "CM 22",
      "CM 22.5",
      "CM 23",
      "CM 23.5",
      "CM 24",
      "CM 24.5",
      "CM 25",
      "CM 25.5",
      "CM 26",
      "CM 26.5",
      "CM 27"
    ]
  },
  {
    "sku_id": "nike-HQ7540-100-白色/Varsity_Red/Dark_Charcoal/Metallic_Gold",
    "brand": "NIKE",
    "parent_id": "HQ7540-100",
    "sku_url": "https://www.nike.com/tw/t/shox-z-5AFJMyDk/HQ7540-100",
    "category": "woman_shoes",
    "product_name": "Nike Shox Z",
    "img_path": "https://static.nike.com/a/images/t_default/u_9ddf04c7-2a9a-4d76-add1-d15af8f0263d,c_scale,fl_relative,w_1.0,h_1.0,fl_layer_apply/e2745252-0cca-4e29-a604-fdc8cf3127f4/W+NIKE+SHOX+Z.png",
    "color_label": "白色/Varsity Red/Dark Charcoal/Metallic Gold",
    "original_price": null,
    "current_price": 4050,
    "full_size_list": [
      "CM 22",
      "CM 22.5",
      "CM 23",
      "CM 23.5",
      "CM 24",
      "CM 24.5",
      "CM 25",
      "CM 25.5",
      "CM 26",
      "CM 26.5",
      "CM 27"
    ],
    "available_list": [
      "CM 22",
      "CM 22.5",
      "CM 23",
      "CM 23.5",
      "CM 24",
      "CM 24.5",
      "CM 25",
      "CM 25.5",
      "CM 26"
    ]
  },
  {
    "sku_id": "nike-HQ7540-401-Midnight_Navy/Metallic_Silver/Dark_Obsidian",
    "brand": "NIKE",
    "parent_id": "HQ7540-401",
    "sku_url": "https://www.nike.com/tw/t/shox-z-5AFJMyDk/HQ7540-401",
    "category": "woman_shoes",
    "product_name": "Nike Shox Z",
    "img_path": "https://static.nike.com/a/images/t_default/u_9ddf04c7-2a9a-4d76-add1-d15af8f0263d,c_scale,fl_relative,w_1.0,h_1.0,fl_layer_apply/70d92aef-1ceb-4f30-9cff-db19c470821b/W+NIKE+SHOX+Z.png",
    "color_label": "Midnight Navy/Metallic Silver/Dark Obsidian",
    "original_price": null,
    "current_price": 4500,
    "full_size_list": [
      "CM 22",
      "CM 22.5",
      "CM 23",
      "CM 23.5",
      "CM 24",
      "CM 24.5",
      "CM 25",
      "CM 25.5",
      "CM 26",
      "CM 26.5",
      "CM 27"
    ],
    "available_list": [
      "CM 22.5",
      "CM 23",
      "CM 23.5",
      "CM 24",
      "CM 24.5",
      "CM 25",
      "CM 25.5",
      "CM 26",
      "CM 26.5",
      "CM 27"
    ]
  },
  {
    "sku_id": "nike-HQ7901-004-黑色/Peony/黑色",
    "brand": "NIKE",
    "parent_id": "HQ7901-004",
    "sku_url": "https://www.nike.com/tw/t/v5-rnr-%E5%85%B7%E5%8F%8D%E5%85%89%E8%A3%9D%E9%A3%BE-XwdKwm/HQ7901-004",
    "category": "woman_shoes",
    "product_name": "Nike V5 RNR",
    "img_path": "https://static.nike.com/a/images/t_default/u_9ddf04c7-2a9a-4d76-add1-d15af8f0263d,c_scale,fl_relative,w_1.0,h_1.0,fl_layer_apply/da85e50b-2b9e-4f1a-994f-f48e237c5e66/W+NIKE+V5+RNR.png",
    "color_label": "黑色/Peony/黑色",
    "original_price": null,
    "current_price": 3100,
    "full_size_list": [
      "CM 22",
      "CM 22.5",
      "CM 23",
      "CM 23.5",
      "CM 24",
      "CM 24.5",
      "CM 25",
      "CM 25.5",
      "CM 26",
      "CM 26.5",
      "CM 27",
      "CM 27.5"
    ],
    "available_list": [
      "CM 22",
      "CM 22.5",
      "CM 23",
      "CM 23.5",
      "CM 24",
      "CM 24.5",
      "CM 25",
      "CM 25.5",
      "CM 26",
      "CM 26.5",
      "CM 27"
    ]
  },
  {
    "sku_id": "nike-HF2882-100-Summit_White/Photon_Dust/Washed_Coral/Iron_Grey",
    "brand": "NIKE",
    "parent_id": "HF2882-100",
    "sku_url": "https://www.nike.com/tw/t/sabrina-3-ep-%E7%B1%83%E7%90%83-G2lc4oD7/HF2882-100",
    "category": "woman_shoes",
    "product_name": "Sabrina 3 \"Silencer\" EP",
    "img_path": "https://static.nike.com/a/images/t_default/u_9ddf04c7-2a9a-4d76-add1-d15af8f0263d,c_scale,fl_relative,w_1.0,h_1.0,fl_layer_apply/f6d256b4-dd65-49d1-8375-e72d6e0fbe6b/SABRINA+3+EP.png",
    "color_label": "Summit White/Photon Dust/Washed Coral/Iron Grey",
    "original_price": null,
    "current_price": 3655,
    "full_size_list": [
      "CM 22",
      "CM 22.5",
      "CM 23",
      "CM 23.5",
      "CM 24",
      "CM 24.5",
      "CM 25",
      "CM 25.5",
      "CM 26",
      "CM 26.5",
      "CM 27",
      "CM 27.5",
      "CM 28",
      "CM 28.5",
      "CM 29",
      "CM 29.5",
      "CM 30",
      "CM 30.5",
      "CM 31",
      "CM 31.5",
      "CM 32.5",
      "CM 33.5"
    ],
    "available_list": [
      "CM 22",
      "CM 30.5"
    ]
  },
  {
    "sku_id": "nike-HF2882-101-白色/Mint_Foam/Metallic_Silver",
    "brand": "NIKE",
    "parent_id": "HF2882-101",
    "sku_url": "https://www.nike.com/tw/t/sabrina-3-ep-%E7%B1%83%E7%90%83-G2lc4oD7/HF2882-101",
    "category": "woman_shoes",
    "product_name": "Sabrina 3 EP",
    "img_path": "https://static.nike.com/a/images/t_default/u_9ddf04c7-2a9a-4d76-add1-d15af8f0263d,c_scale,fl_relative,w_1.0,h_1.0,fl_layer_apply/bcce47be-9654-41f3-a63f-331602bc3486/SABRINA+3+EP.png",
    "color_label": "白色/Mint Foam/Metallic Silver",
    "original_price": null,
    "current_price": 3870,
    "full_size_list": [
      "CM 22",
      "CM 22.5",
      "CM 23",
      "CM 23.5",
      "CM 24",
      "CM 24.5",
      "CM 25",
      "CM 25.5",
      "CM 26",
      "CM 26.5",
      "CM 27",
      "CM 27.5",
      "CM 28",
      "CM 28.5",
      "CM 29",
      "CM 29.5",
      "CM 30",
      "CM 30.5",
      "CM 31"
    ],
    "available_list": [
      "CM 22",
      "CM 22.5",
      "CM 23",
      "CM 23.5",
      "CM 24",
      "CM 24.5",
      "CM 25",
      "CM 25.5",
      "CM 26",
      "CM 26.5",
      "CM 27",
      "CM 27.5",
      "CM 28.5",
      "CM 29.5",
      "CM 30.5",
      "CM 31"
    ]
  },
  {
    "sku_id": "nike-HF2882-800-Crimson_Tint/Arctic_Punch/Light_Current_Blue/黑色",
    "brand": "NIKE",
    "parent_id": "HF2882-800",
    "sku_url": "https://www.nike.com/tw/t/sabrina-3-ep-%E7%B1%83%E7%90%83-G2lc4oD7/HF2882-800",
    "category": "woman_shoes",
    "product_name": "Sabrina 3 EP",
    "img_path": "https://static.nike.com/a/images/t_default/u_9ddf04c7-2a9a-4d76-add1-d15af8f0263d,c_scale,fl_relative,w_1.0,h_1.0,fl_layer_apply/7c7d0fa2-b6c4-4c14-9b77-464760b014f2/SABRINA+3+EP.png",
    "color_label": "Crimson Tint/Arctic Punch/Light Current Blue/黑色",
    "original_price": null,
    "current_price": 4300,
    "full_size_list": [
      "CM 22",
      "CM 22.5",
      "CM 23",
      "CM 23.5",
      "CM 24",
      "CM 24.5",
      "CM 25",
      "CM 25.5",
      "CM 26",
      "CM 26.5",
      "CM 27",
      "CM 27.5",
      "CM 28",
      "CM 28.5",
      "CM 29",
      "CM 29.5",
      "CM 30.5"
    ],
    "available_list": [
      "CM 22",
      "CM 22.5",
      "CM 23",
      "CM 23.5",
      "CM 24",
      "CM 24.5",
      "CM 25",
      "CM 25.5",
      "CM 26",
      "CM 26.5",
      "CM 27",
      "CM 27.5",
      "CM 28",
      "CM 28.5",
      "CM 29",
      "CM 29.5",
      "CM 30.5"
    ]
  },
  {
    "sku_id": "nike-HF2882-400-Glacier_Blue/Light_Armory_Blue/Still_Blue/Metallic_Gold",
    "brand": "NIKE",
    "parent_id": "HF2882-400",
    "sku_url": "https://www.nike.com/tw/t/sabrina-3-ep-%E7%B1%83%E7%90%83-G2lc4oD7/HF2882-400",
    "category": "woman_shoes",
    "product_name": "Sabrina 3 \"Blueprint\" EP",
    "img_path": "https://static.nike.com/a/images/t_default/u_9ddf04c7-2a9a-4d76-add1-d15af8f0263d,c_scale,fl_relative,w_1.0,h_1.0,fl_layer_apply/7225074b-f079-4b33-b2a8-cdd12df52021/SABRINA+3+EP.png",
    "color_label": "Glacier Blue/Light Armory Blue/Still Blue/Metallic Gold",
    "original_price": null,
    "current_price": 3870,
    "full_size_list": [
      "CM 22",
      "CM 22.5",
      "CM 23",
      "CM 23.5",
      "CM 24",
      "CM 24.5",
      "CM 25",
      "CM 25.5",
      "CM 26",
      "CM 26.5",
      "CM 27",
      "CM 27.5",
      "CM 28",
      "CM 28.5",
      "CM 29",
      "CM 29.5",
      "CM 30",
      "CM 30.5",
      "CM 31",
      "CM 31.5",
      "CM 32.5",
      "CM 33.5"
    ],
    "available_list": [
      "CM 23",
      "CM 26",
      "CM 26.5",
      "CM 27",
      "CM 27.5",
      "CM 28",
      "CM 28.5",
      "CM 29",
      "CM 29.5",
      "CM 30.5",
      "CM 31"
    ]
  },
  {
    "sku_id": "nike-HF2882-500-Barely_Grape/Magic_Ember/Bright_Peach/黑色",
    "brand": "NIKE",
    "parent_id": "HF2882-500",
    "sku_url": "https://www.nike.com/tw/t/sabrina-3-ep-%E7%B1%83%E7%90%83-G2lc4oD7/HF2882-500",
    "category": "woman_shoes",
    "product_name": "Sabrina 3 \"Radiant\" EP",
    "img_path": "https://static.nike.com/a/images/t_default/u_9ddf04c7-2a9a-4d76-add1-d15af8f0263d,c_scale,fl_relative,w_1.0,h_1.0,fl_layer_apply/12773e65-3c79-445a-9a13-592b0f6f1ca4/SABRINA+3+EP.png",
    "color_label": "Barely Grape/Magic Ember/Bright Peach/黑色",
    "original_price": null,
    "current_price": 3870,
    "full_size_list": [
      "CM 22",
      "CM 22.5",
      "CM 23",
      "CM 23.5",
      "CM 24",
      "CM 24.5",
      "CM 25",
      "CM 25.5",
      "CM 26",
      "CM 26.5",
      "CM 27",
      "CM 27.5",
      "CM 28",
      "CM 28.5",
      "CM 29",
      "CM 29.5",
      "CM 30",
      "CM 30.5",
      "CM 31",
      "CM 31.5",
      "CM 32",
      "CM 32.5",
      "CM 33.5"
    ],
    "available_list": [
      "CM 22",
      "CM 22.5",
      "CM 23",
      "CM 23.5",
      "CM 24",
      "CM 24.5",
      "CM 25",
      "CM 25.5",
      "CM 26",
      "CM 26.5",
      "CM 27",
      "CM 27.5",
      "CM 28",
      "CM 28.5",
      "CM 29",
      "CM 29.5",
      "CM 30",
      "CM 30.5",
      "CM 31"
    ]
  },
  {
    "sku_id": "nike-HF2882-001-黑色/Dark_Smoke_Grey/Iron_Grey/白色",
    "brand": "NIKE",
    "parent_id": "HF2882-001",
    "sku_url": "https://www.nike.com/tw/t/sabrina-3-ep-%E7%B1%83%E7%90%83-G2lc4oD7/HF2882-001",
    "category": "woman_shoes",
    "product_name": "Sabrina 3 EP",
    "img_path": "https://static.nike.com/a/images/t_default/u_9ddf04c7-2a9a-4d76-add1-d15af8f0263d,c_scale,fl_relative,w_1.0,h_1.0,fl_layer_apply/a599a446-9313-47df-b88f-af02aa426118/SABRINA+3+EP.png",
    "color_label": "黑色/Dark Smoke Grey/Iron Grey/白色",
    "original_price": null,
    "current_price": 4300,
    "full_size_list": [
      "CM 22",
      "CM 22.5",
      "CM 23",
      "CM 23.5",
      "CM 24",
      "CM 24.5",
      "CM 25",
      "CM 25.5",
      "CM 26",
      "CM 26.5",
      "CM 27",
      "CM 27.5",
      "CM 28",
      "CM 28.5",
      "CM 29",
      "CM 29.5",
      "CM 30.5"
    ],
    "available_list": [
      "CM 22",
      "CM 22.5",
      "CM 23",
      "CM 23.5",
      "CM 24",
      "CM 24.5",
      "CM 25",
      "CM 25.5",
      "CM 26",
      "CM 26.5",
      "CM 27",
      "CM 27.5",
      "CM 28",
      "CM 28.5",
      "CM 29",
      "CM 29.5"
    ]
  },
  {
    "sku_id": "nike-HF2882-002-Iron_Grey/Barely_Volt/Mint_Foam/Aluminum",
    "brand": "NIKE",
    "parent_id": "HF2882-002",
    "sku_url": "https://www.nike.com/tw/t/sabrina-3-ep-%E7%B1%83%E7%90%83-G2lc4oD7/HF2882-002",
    "category": "woman_shoes",
    "product_name": "Sabrina 3 EP",
    "img_path": "https://static.nike.com/a/images/t_default/u_9ddf04c7-2a9a-4d76-add1-d15af8f0263d,c_scale,fl_relative,w_1.0,h_1.0,fl_layer_apply/1ae3e7a6-83b9-4ef1-a46a-6de0d93345ec/SABRINA+3+EP.png",
    "color_label": "Iron Grey/Barely Volt/Mint Foam/Aluminum",
    "original_price": null,
    "current_price": 4300,
    "full_size_list": [
      "CM 22",
      "CM 22.5",
      "CM 23",
      "CM 23.5",
      "CM 24",
      "CM 24.5",
      "CM 25",
      "CM 25.5",
      "CM 26",
      "CM 26.5",
      "CM 27",
      "CM 27.5",
      "CM 28",
      "CM 28.5",
      "CM 29",
      "CM 29.5",
      "CM 30",
      "CM 31"
    ],
    "available_list": [
      "CM 22",
      "CM 22.5",
      "CM 23",
      "CM 23.5",
      "CM 24",
      "CM 24.5",
      "CM 25",
      "CM 25.5",
      "CM 26",
      "CM 26.5",
      "CM 27",
      "CM 27.5",
      "CM 28",
      "CM 28.5",
      "CM 29",
      "CM 29.5",
      "CM 30",
      "CM 31"
    ]
  },
  {
    "sku_id": "nike-HF2882-600-Pink_Oxford/Reb_Stardust/Enamel_Green/Coconut_Milk",
    "brand": "NIKE",
    "parent_id": "HF2882-600",
    "sku_url": "https://www.nike.com/tw/t/sabrina-3-ep-%E7%B1%83%E7%90%83-G2lc4oD7/HF2882-600",
    "category": "woman_shoes",
    "product_name": "Sabrina 3 EP",
    "img_path": "https://static.nike.com/a/images/t_default/u_9ddf04c7-2a9a-4d76-add1-d15af8f0263d,c_scale,fl_relative,w_1.0,h_1.0,fl_layer_apply/85c29a62-4b60-4dde-acb8-8ebb1c03bcaf/SABRINA+3+EP.png",
    "color_label": "Pink Oxford/Reb Stardust/Enamel Green/Coconut Milk",
    "original_price": null,
    "current_price": 4300,
    "full_size_list": [
      "CM 22",
      "CM 22.5",
      "CM 23",
      "CM 23.5",
      "CM 24",
      "CM 24.5",
      "CM 25",
      "CM 25.5",
      "CM 26",
      "CM 26.5",
      "CM 27",
      "CM 27.5",
      "CM 28",
      "CM 28.5",
      "CM 29",
      "CM 29.5",
      "CM 30",
      "CM 31"
    ],
    "available_list": [
      "CM 22",
      "CM 22.5",
      "CM 23",
      "CM 23.5",
      "CM 24",
      "CM 24.5",
      "CM 25",
      "CM 25.5",
      "CM 26",
      "CM 26.5",
      "CM 27",
      "CM 27.5",
      "CM 28",
      "CM 28.5",
      "CM 29",
      "CM 29.5",
      "CM 30",
      "CM 31"
    ]
  },
  {
    "sku_id": "nike-HF2882-003-Phantom/Ivory/Rush_Coral/黑色",
    "brand": "NIKE",
    "parent_id": "HF2882-003",
    "sku_url": "https://www.nike.com/tw/t/sabrina-3-ep-%E7%B1%83%E7%90%83-G2lc4oD7/HF2882-003",
    "category": "woman_shoes",
    "product_name": "Sabrina 3 EP",
    "img_path": "https://static.nike.com/a/images/t_default/08e01dcf-c278-4bc8-8242-4f18f23bc2f3/SABRINA+3+EP.png",
    "color_label": "Phantom/Ivory/Rush Coral/黑色",
    "original_price": null,
    "current_price": 4300,
    "full_size_list": [
      "CM 22",
      "CM 22.5",
      "CM 23",
      "CM 23.5",
      "CM 24",
      "CM 24.5",
      "CM 25",
      "CM 25.5",
      "CM 26",
      "CM 26.5",
      "CM 27",
      "CM 27.5",
      "CM 28",
      "CM 28.5",
      "CM 29",
      "CM 29.5",
      "CM 30",
      "CM 31"
    ],
    "available_list": [
      "CM 22",
      "CM 22.5",
      "CM 23",
      "CM 23.5",
      "CM 24",
      "CM 24.5",
      "CM 25",
      "CM 25.5",
      "CM 26",
      "CM 26.5",
      "CM 27",
      "CM 27.5",
      "CM 28",
      "CM 28.5",
      "CM 29",
      "CM 29.5",
      "CM 30",
      "CM 31"
    ]
  },
  {
    "sku_id": "nike-HF2882-301-Clay_Green/Seafoam/Volt_Tint/Sequoia",
    "brand": "NIKE",
    "parent_id": "HF2882-301",
    "sku_url": "https://www.nike.com/tw/t/sabrina-3-ep-%E7%B1%83%E7%90%83-G2lc4oD7/HF2882-301",
    "category": "woman_shoes",
    "product_name": "Sabrina 3 EP",
    "img_path": "https://static.nike.com/a/images/t_default/u_9ddf04c7-2a9a-4d76-add1-d15af8f0263d,c_scale,fl_relative,w_1.0,h_1.0,fl_layer_apply/9d532656-b1dc-4f1e-8f20-07e8c148ca69/SABRINA+3+EP.png",
    "color_label": "Clay Green/Seafoam/Volt Tint/Sequoia",
    "original_price": null,
    "current_price": 4300,
    "full_size_list": [
      "CM 22",
      "CM 22.5",
      "CM 23",
      "CM 23.5",
      "CM 24",
      "CM 24.5",
      "CM 25",
      "CM 25.5",
      "CM 26",
      "CM 26.5",
      "CM 27",
      "CM 27.5",
      "CM 28",
      "CM 28.5",
      "CM 29",
      "CM 29.5",
      "CM 30.5"
    ],
    "available_list": [
      "CM 22",
      "CM 22.5",
      "CM 23",
      "CM 23.5",
      "CM 24",
      "CM 24.5",
      "CM 25",
      "CM 25.5",
      "CM 26",
      "CM 26.5",
      "CM 27",
      "CM 27.5",
      "CM 28",
      "CM 28.5",
      "CM 29",
      "CM 29.5",
      "CM 30.5"
    ]
  },
  {
    "sku_id": "nike-IQ1145-610-暗粉紅/Light_Bone/Burgundy_Crush/Sail",
    "brand": "NIKE",
    "parent_id": "IQ1145-610",
    "sku_url": "https://www.nike.com/tw/t/dunk-%E4%BD%8E%E7%AD%92-sp0IyfLU/IQ1145-610",
    "category": "woman_shoes",
    "product_name": "Nike Dunk 低筒",
    "img_path": "https://static.nike.com/a/images/t_default/u_9ddf04c7-2a9a-4d76-add1-d15af8f0263d,c_scale,fl_relative,w_1.0,h_1.0,fl_layer_apply/6fac466a-c4b0-4c42-aa7d-db3e58d3d4b3/W+NIKE+DUNK+LOW.png",
    "color_label": "暗粉紅/Light Bone/Burgundy Crush/Sail",
    "original_price": null,
    "current_price": 3800,
    "full_size_list": [
      "CM 22",
      "CM 22.5",
      "CM 23",
      "CM 23.5",
      "CM 24",
      "CM 24.5",
      "CM 25",
      "CM 25.5",
      "CM 26",
      "CM 26.5",
      "CM 27"
    ],
    "available_list": [
      "CM 22.5"
    ]
  },
  {
    "sku_id": "nike-FJ7126-001-黑色/白色",
    "brand": "NIKE",
    "parent_id": "FJ7126-001",
    "sku_url": "https://www.nike.com/tw/t/free-metcon-6-%E5%81%A5%E8%BA%AB%E8%A8%93%E7%B7%B4-Q3pWcF/FJ7126-001",
    "category": "woman_shoes",
    "product_name": "Nike Free Metcon 6",
    "img_path": "https://static.nike.com/a/images/t_default/u_9ddf04c7-2a9a-4d76-add1-d15af8f0263d,c_scale,fl_relative,w_1.0,h_1.0,fl_layer_apply/db7813d0-a95b-4222-bf49-54f558426b42/W+NIKE+FREE+METCON+6.png",
    "color_label": "黑色/白色",
    "original_price": null,
    "current_price": 3600,
    "full_size_list": [
      "CM 22",
      "CM 22.5",
      "CM 23",
      "CM 23.5",
      "CM 24",
      "CM 24.5",
      "CM 25",
      "CM 25.5",
      "CM 26",
      "CM 26.5",
      "CM 27",
      "CM 27.5"
    ],
    "available_list": [
      "CM 24.5",
      "CM 25.5",
      "CM 26.5"
    ]
  },
  {
    "sku_id": "nike-FJ7126-003-黑色/Anthracite",
    "brand": "NIKE",
    "parent_id": "FJ7126-003",
    "sku_url": "https://www.nike.com/tw/t/free-metcon-6-%E5%81%A5%E8%BA%AB%E8%A8%93%E7%B7%B4-Q3pWcF/FJ7126-003",
    "category": "woman_shoes",
    "product_name": "Nike Free Metcon 6",
    "img_path": "https://static.nike.com/a/images/t_default/u_9ddf04c7-2a9a-4d76-add1-d15af8f0263d,c_scale,fl_relative,w_1.0,h_1.0,fl_layer_apply/20cfea87-32d7-4780-9b7b-43b181c42745/W+NIKE+FREE+METCON+6.png",
    "color_label": "黑色/Anthracite",
    "original_price": null,
    "current_price": 4000,
    "full_size_list": [
      "CM 22",
      "CM 22.5",
      "CM 23",
      "CM 23.5",
      "CM 24",
      "CM 24.5",
      "CM 25",
      "CM 25.5",
      "CM 26",
      "CM 26.5",
      "CM 27"
    ],
    "available_list": [
      "CM 22",
      "CM 23",
      "CM 23.5",
      "CM 24",
      "CM 24.5",
      "CM 25",
      "CM 25.5",
      "CM 26",
      "CM 26.5"
    ]
  },
  {
    "sku_id": "nike-FJ7126-605-Particle_Pink/Pale_Ivory/Red_Sepia/Metallic_Rose_Gold",
    "brand": "NIKE",
    "parent_id": "FJ7126-605",
    "sku_url": "https://www.nike.com/tw/t/free-metcon-6-%E5%81%A5%E8%BA%AB%E8%A8%93%E7%B7%B4-Q3pWcF/FJ7126-605",
    "category": "woman_shoes",
    "product_name": "Nike Free Metcon 6",
    "img_path": "https://static.nike.com/a/images/t_default/u_9ddf04c7-2a9a-4d76-add1-d15af8f0263d,c_scale,fl_relative,w_1.0,h_1.0,fl_layer_apply/d28135ab-8438-412e-a7a6-3c8a05c5a4b7/W+NIKE+FREE+METCON+6.png",
    "color_label": "Particle Pink/Pale Ivory/Red Sepia/Metallic Rose Gold",
    "original_price": null,
    "current_price": 3600,
    "full_size_list": [
      "CM 22",
      "CM 22.5",
      "CM 23",
      "CM 23.5",
      "CM 24",
      "CM 24.5",
      "CM 25",
      "CM 25.5",
      "CM 26",
      "CM 26.5",
      "CM 27",
      "CM 27.5",
      "CM 28.5"
    ],
    "available_list": [
      "CM 23.5",
      "CM 24",
      "CM 24.5",
      "CM 25",
      "CM 25.5"
    ]
  },
  {
    "sku_id": "nike-FJ7126-606-暗粉紅/Reb_Stardust/Red_Sepia",
    "brand": "NIKE",
    "parent_id": "FJ7126-606",
    "sku_url": "https://www.nike.com/tw/t/free-metcon-6-%E5%81%A5%E8%BA%AB%E8%A8%93%E7%B7%B4-Q3pWcF/FJ7126-606",
    "category": "woman_shoes",
    "product_name": "Nike Free Metcon 6",
    "img_path": "https://static.nike.com/a/images/t_default/u_9ddf04c7-2a9a-4d76-add1-d15af8f0263d,c_scale,fl_relative,w_1.0,h_1.0,fl_layer_apply/e073acf6-10a8-4b43-ae30-ddffce863a90/W+NIKE+FREE+METCON+6.png",
    "color_label": "暗粉紅/Reb Stardust/Red Sepia",
    "original_price": null,
    "current_price": 3600,
    "full_size_list": [
      "CM 22",
      "CM 22.5",
      "CM 23",
      "CM 23.5",
      "CM 24",
      "CM 24.5",
      "CM 25",
      "CM 25.5",
      "CM 26",
      "CM 26.5",
      "CM 27",
      "CM 27.5",
      "CM 28.5"
    ],
    "available_list": [
      "CM 22",
      "CM 22.5",
      "CM 24",
      "CM 24.5",
      "CM 25",
      "CM 25.5",
      "CM 26"
    ]
  },
  {
    "sku_id": "nike-FJ7126-608-Sweet_Beet/Noble_Red/Burgundy_Crush",
    "brand": "NIKE",
    "parent_id": "FJ7126-608",
    "sku_url": "https://www.nike.com/tw/t/free-metcon-6-%E5%81%A5%E8%BA%AB%E8%A8%93%E7%B7%B4-Q3pWcF/FJ7126-608",
    "category": "woman_shoes",
    "product_name": "Nike Free Metcon 6",
    "img_path": "https://static.nike.com/a/images/t_default/u_9ddf04c7-2a9a-4d76-add1-d15af8f0263d,c_scale,fl_relative,w_1.0,h_1.0,fl_layer_apply/e2f63ec1-950a-4516-8dd9-87de99bdddf0/W+NIKE+FREE+METCON+6.png",
    "color_label": "Sweet Beet/Noble Red/Burgundy Crush",
    "original_price": null,
    "current_price": 3600,
    "full_size_list": [
      "CM 22",
      "CM 22.5",
      "CM 23",
      "CM 23.5",
      "CM 24",
      "CM 24.5",
      "CM 25",
      "CM 25.5",
      "CM 26",
      "CM 26.5",
      "CM 27"
    ],
    "available_list": [
      "CM 22",
      "CM 22.5",
      "CM 23",
      "CM 23.5",
      "CM 24",
      "CM 24.5",
      "CM 25",
      "CM 25.5",
      "CM 26",
      "CM 26.5",
      "CM 27"
    ]
  },
  {
    "sku_id": "nike-FJ7126-012-Soft_Pearl/Pearl_White/黑色",
    "brand": "NIKE",
    "parent_id": "FJ7126-012",
    "sku_url": "https://www.nike.com/tw/t/free-metcon-6-%E5%81%A5%E8%BA%AB%E8%A8%93%E7%B7%B4-Q3pWcF/FJ7126-012",
    "category": "woman_shoes",
    "product_name": "Nike Free Metcon 6",
    "img_path": "https://static.nike.com/a/images/t_default/u_9ddf04c7-2a9a-4d76-add1-d15af8f0263d,c_scale,fl_relative,w_1.0,h_1.0,fl_layer_apply/aef2f90a-12c2-4924-b7df-33e420e0e517/W+NIKE+FREE+METCON+6.png",
    "color_label": "Soft Pearl/Pearl White/黑色",
    "original_price": null,
    "current_price": 3200,
    "full_size_list": [
      "CM 22",
      "CM 22.5",
      "CM 23",
      "CM 23.5",
      "CM 24",
      "CM 24.5",
      "CM 25",
      "CM 25.5",
      "CM 26",
      "CM 26.5",
      "CM 27",
      "CM 27.5",
      "CM 28.5"
    ],
    "available_list": [
      "CM 22.5",
      "CM 23.5",
      "CM 24",
      "CM 24.5",
      "CM 25",
      "CM 25.5",
      "CM 26",
      "CM 27"
    ]
  },
  {
    "sku_id": "nike-FJ7126-110-白色/Half_Blue/Metallic_Silver",
    "brand": "NIKE",
    "parent_id": "FJ7126-110",
    "sku_url": "https://www.nike.com/tw/t/free-metcon-6-%E5%81%A5%E8%BA%AB%E8%A8%93%E7%B7%B4-Q3pWcF/FJ7126-110",
    "category": "woman_shoes",
    "product_name": "Nike Free Metcon 6",
    "img_path": "https://static.nike.com/a/images/t_default/u_9ddf04c7-2a9a-4d76-add1-d15af8f0263d,c_scale,fl_relative,w_1.0,h_1.0,fl_layer_apply/5aeb599d-4ea1-4141-8dfb-e61056c53245/W+NIKE+FREE+METCON+6.png",
    "color_label": "白色/Half Blue/Metallic Silver",
    "original_price": null,
    "current_price": 4000,
    "full_size_list": [
      "CM 22",
      "CM 22.5",
      "CM 23",
      "CM 23.5",
      "CM 24",
      "CM 24.5",
      "CM 25",
      "CM 25.5",
      "CM 26",
      "CM 26.5",
      "CM 27",
      "CM 27.5",
      "CM 28.5"
    ],
    "available_list": [
      "CM 22",
      "CM 22.5",
      "CM 23",
      "CM 23.5",
      "CM 24",
      "CM 24.5",
      "CM 25",
      "CM 25.5",
      "CM 26",
      "CM 26.5"
    ]
  },
  {
    "sku_id": "nike-FJ7126-200-Light_Violet_Ore/Violet_Ore/Chalk/Tattoo",
    "brand": "NIKE",
    "parent_id": "FJ7126-200",
    "sku_url": "https://www.nike.com/tw/t/free-metcon-6-%E5%81%A5%E8%BA%AB%E8%A8%93%E7%B7%B4-Q3pWcF/FJ7126-200",
    "category": "woman_shoes",
    "product_name": "Nike Free Metcon 6",
    "img_path": "https://static.nike.com/a/images/t_default/u_9ddf04c7-2a9a-4d76-add1-d15af8f0263d,c_scale,fl_relative,w_1.0,h_1.0,fl_layer_apply/e9eddbd7-44fd-4f76-b2df-1c2d43fe50e0/W+NIKE+FREE+METCON+6.png",
    "color_label": "Light Violet Ore/Violet Ore/Chalk/Tattoo",
    "original_price": null,
    "current_price": 4000,
    "full_size_list": [
      "CM 22",
      "CM 22.5",
      "CM 23",
      "CM 23.5",
      "CM 24",
      "CM 24.5",
      "CM 25",
      "CM 25.5",
      "CM 26",
      "CM 26.5",
      "CM 27",
      "CM 27.5",
      "CM 28.5"
    ],
    "available_list": [
      "CM 22",
      "CM 22.5",
      "CM 23",
      "CM 23.5",
      "CM 24",
      "CM 24.5",
      "CM 25",
      "CM 25.5",
      "CM 26",
      "CM 26.5",
      "CM 27",
      "CM 27.5"
    ]
  },
  {
    "sku_id": "nike-FJ7126-112-Chalk/Summit_White/Pure_Platinum",
    "brand": "NIKE",
    "parent_id": "FJ7126-112",
    "sku_url": "https://www.nike.com/tw/t/free-metcon-6-%E5%81%A5%E8%BA%AB%E8%A8%93%E7%B7%B4-Q3pWcF/FJ7126-112",
    "category": "woman_shoes",
    "product_name": "Nike Free Metcon 6",
    "img_path": "https://static.nike.com/a/images/t_default/u_9ddf04c7-2a9a-4d76-add1-d15af8f0263d,c_scale,fl_relative,w_1.0,h_1.0,fl_layer_apply/02789bc3-7568-40f8-8f82-534a95e921b8/W+NIKE+FREE+METCON+6.png",
    "color_label": "Chalk/Summit White/Pure Platinum",
    "original_price": null,
    "current_price": 4000,
    "full_size_list": [
      "CM 23",
      "CM 22",
      "CM 22.5",
      "CM 23.5",
      "CM 24",
      "CM 24.5",
      "CM 25",
      "CM 25.5",
      "CM 26",
      "CM 26.5",
      "CM 27",
      "CM 27.5"
    ],
    "available_list": [
      "CM 23",
      "CM 22",
      "CM 22.5",
      "CM 23.5",
      "CM 24",
      "CM 24.5",
      "CM 25",
      "CM 25.5",
      "CM 26",
      "CM 26.5",
      "CM 27",
      "CM 27.5"
    ]
  },
  {
    "sku_id": "nike-FJ7126-114-白色/Violet_Mist/Chalk/Hot_Lava",
    "brand": "NIKE",
    "parent_id": "FJ7126-114",
    "sku_url": "https://www.nike.com/tw/t/free-metcon-6-%E5%81%A5%E8%BA%AB%E8%A8%93%E7%B7%B4-Q3pWcF/FJ7126-114",
    "category": "woman_shoes",
    "product_name": "Nike Free Metcon 6",
    "img_path": "https://static.nike.com/a/images/t_default/u_9ddf04c7-2a9a-4d76-add1-d15af8f0263d,c_scale,fl_relative,w_1.0,h_1.0,fl_layer_apply/0225effa-53b2-4615-ab87-2f8a7e0c19be/W+NIKE+FREE+METCON+6.png",
    "color_label": "白色/Violet Mist/Chalk/Hot Lava",
    "original_price": null,
    "current_price": 4000,
    "full_size_list": [
      "CM 24",
      "CM 22",
      "CM 22.5",
      "CM 23",
      "CM 23.5",
      "CM 24.5",
      "CM 25",
      "CM 25.5",
      "CM 26",
      "CM 26.5",
      "CM 27",
      "CM 27.5"
    ],
    "available_list": [
      "CM 24",
      "CM 22",
      "CM 22.5",
      "CM 23",
      "CM 23.5",
      "CM 24.5",
      "CM 25",
      "CM 25.5",
      "CM 26",
      "CM 26.5",
      "CM 27"
    ]
  },
  {
    "sku_id": "nike-FD0736-003-Pure_Platinum/Wolf_Grey/Cool_Grey/Metallic_Cool_Grey",
    "brand": "NIKE",
    "parent_id": "FD0736-003",
    "sku_url": "https://www.nike.com/tw/t/v2k-run-%E5%85%B7%E5%8F%8D%E5%85%89%E8%A3%9D%E9%A3%BE-zJV8TV/FD0736-003",
    "category": "woman_shoes",
    "product_name": "Nike V2K Run",
    "img_path": "https://static.nike.com/a/images/t_default/u_9ddf04c7-2a9a-4d76-add1-d15af8f0263d,c_scale,fl_relative,w_1.0,h_1.0,fl_layer_apply/a200f9ed-aefe-4f27-89c0-dc861f23c0e1/W+NIKE+V2K+RUN.png",
    "color_label": "Pure Platinum/Wolf Grey/Cool Grey/Metallic Cool Grey",
    "original_price": null,
    "current_price": 3800,
    "full_size_list": [
      "CM 22",
      "CM 22.5",
      "CM 23",
      "CM 23.5",
      "CM 24",
      "CM 24.5",
      "CM 25",
      "CM 25.5",
      "CM 26",
      "CM 26.5",
      "CM 27"
    ],
    "available_list": [
      "CM 22",
      "CM 24",
      "CM 25",
      "CM 25.5",
      "CM 26"
    ]
  },
  {
    "sku_id": "nike-FD0736-100-Summit_White/Pure_Platinum/Light_Iron_Ore/Metallic_Silver",
    "brand": "NIKE",
    "parent_id": "FD0736-100",
    "sku_url": "https://www.nike.com/tw/t/v2k-run-%E5%85%B7%E5%8F%8D%E5%85%89%E8%A3%9D%E9%A3%BE-zJV8TV/FD0736-100",
    "category": "woman_shoes",
    "product_name": "Nike V2K Run",
    "img_path": "https://static.nike.com/a/images/t_default/u_9ddf04c7-2a9a-4d76-add1-d15af8f0263d,c_scale,fl_relative,w_1.0,h_1.0,fl_layer_apply/3e8455ad-c00c-4996-a85a-b5c4d38c6ae2/W+NIKE+V2K+RUN.png",
    "color_label": "Summit White/Pure Platinum/Light Iron Ore/Metallic Silver",
    "original_price": null,
    "current_price": 3800,
    "full_size_list": [
      "CM 22",
      "CM 22.5",
      "CM 23",
      "CM 23.5",
      "CM 24",
      "CM 24.5",
      "CM 25",
      "CM 25.5",
      "CM 26",
      "CM 26.5",
      "CM 27",
      "CM 27.5",
      "CM 28",
      "CM 28.5"
    ],
    "available_list": [
      "CM 22",
      "CM 23",
      "CM 23.5",
      "CM 24",
      "CM 24.5",
      "CM 25",
      "CM 25.5",
      "CM 26",
      "CM 26.5"
    ]
  },
  {
    "sku_id": "nike-FD0736-009-Platinum_Tint/Summit_White/Light_Smoke_Grey/Platinum_Tint",
    "brand": "NIKE",
    "parent_id": "FD0736-009",
    "sku_url": "https://www.nike.com/tw/t/v2k-run-%E5%85%B7%E5%8F%8D%E5%85%89%E8%A3%9D%E9%A3%BE-zJV8TV/FD0736-009",
    "category": "woman_shoes",
    "product_name": "Nike V2K Run",
    "img_path": "https://static.nike.com/a/images/t_default/u_9ddf04c7-2a9a-4d76-add1-d15af8f0263d,c_scale,fl_relative,w_1.0,h_1.0,fl_layer_apply/f4d9daed-58be-4d43-9382-f511ebefb531/W+NIKE+V2K+RUN.png",
    "color_label": "Platinum Tint/Summit White/Light Smoke Grey/Platinum Tint",
    "original_price": null,
    "current_price": 3800,
    "full_size_list": [
      "CM 22",
      "CM 22.5",
      "CM 23",
      "CM 23.5",
      "CM 24",
      "CM 24.5",
      "CM 25",
      "CM 25.5",
      "CM 26",
      "CM 26.5",
      "CM 27"
    ],
    "available_list": [
      "CM 22",
      "CM 22.5",
      "CM 23",
      "CM 23.5",
      "CM 24",
      "CM 24.5",
      "CM 25",
      "CM 25.5",
      "CM 26",
      "CM 26.5"
    ]
  },
  {
    "sku_id": "nike-FD0736-112-白色/Summit_White/College_Grey/Particle_Pink",
    "brand": "NIKE",
    "parent_id": "FD0736-112",
    "sku_url": "https://www.nike.com/tw/t/v2k-run-%E5%85%B7%E5%8F%8D%E5%85%89%E8%A3%9D%E9%A3%BE-zJV8TV/FD0736-112",
    "category": "woman_shoes",
    "product_name": "Nike V2K Run",
    "img_path": "https://static.nike.com/a/images/t_default/u_9ddf04c7-2a9a-4d76-add1-d15af8f0263d,c_scale,fl_relative,w_1.0,h_1.0,fl_layer_apply/195a83cd-ad0f-49d4-b718-3efd0eaab96c/W+NIKE+V2K+RUN.png",
    "color_label": "白色/Summit White/College Grey/Particle Pink",
    "original_price": null,
    "current_price": 3420,
    "full_size_list": [
      "CM 22",
      "CM 22.5",
      "CM 23",
      "CM 23.5",
      "CM 24",
      "CM 24.5",
      "CM 25",
      "CM 25.5",
      "CM 26",
      "CM 26.5",
      "CM 27",
      "CM 27.5",
      "CM 28",
      "CM 28.5",
      "CM 29"
    ],
    "available_list": [
      "CM 22",
      "CM 22.5",
      "CM 23",
      "CM 26",
      "CM 26.5",
      "CM 27",
      "CM 28"
    ]
  },
  {
    "sku_id": "nike-FD0736-114-Summit_White/Vast_Grey/Alabaster/Pink_Spell",
    "brand": "NIKE",
    "parent_id": "FD0736-114",
    "sku_url": "https://www.nike.com/tw/t/v2k-run-%E5%85%B7%E5%8F%8D%E5%85%89%E8%A3%9D%E9%A3%BE-zJV8TV/FD0736-114",
    "category": "woman_shoes",
    "product_name": "Nike V2K Run",
    "img_path": "https://static.nike.com/a/images/t_default/u_9ddf04c7-2a9a-4d76-add1-d15af8f0263d,c_scale,fl_relative,w_1.0,h_1.0,fl_layer_apply/8f4eae9d-9e14-44a8-baaa-405f76b13b14/W+NIKE+V2K+RUN.png",
    "color_label": "Summit White/Vast Grey/Alabaster/Pink Spell",
    "original_price": null,
    "current_price": 3040,
    "full_size_list": [
      "CM 22",
      "CM 22.5",
      "CM 23",
      "CM 23.5",
      "CM 24",
      "CM 24.5",
      "CM 25",
      "CM 25.5",
      "CM 26",
      "CM 26.5",
      "CM 27"
    ],
    "available_list": [
      "CM 22",
      "CM 22.5",
      "CM 23",
      "CM 23.5",
      "CM 24",
      "CM 24.5",
      "CM 25",
      "CM 25.5",
      "CM 26",
      "CM 26.5",
      "CM 27"
    ]
  },
  {
    "sku_id": "nike-FD0736-115-Sanddrift/Shimmer/Fauna_Brown/Pink_Foam",
    "brand": "NIKE",
    "parent_id": "FD0736-115",
    "sku_url": "https://www.nike.com/tw/t/v2k-run-%E5%85%B7%E5%8F%8D%E5%85%89%E8%A3%9D%E9%A3%BE-zJV8TV/FD0736-115",
    "category": "woman_shoes",
    "product_name": "Nike V2K Run",
    "img_path": "https://static.nike.com/a/images/t_default/u_9ddf04c7-2a9a-4d76-add1-d15af8f0263d,c_scale,fl_relative,w_1.0,h_1.0,fl_layer_apply/57aec1ad-46a8-4671-ba4c-1cd251a36b21/W+NIKE+V2K+RUN.png",
    "color_label": "Sanddrift/Shimmer/Fauna Brown/Pink Foam",
    "original_price": null,
    "current_price": 3800,
    "full_size_list": [
      "CM 22",
      "CM 22.5",
      "CM 23",
      "CM 23.5",
      "CM 24",
      "CM 24.5",
      "CM 25",
      "CM 25.5",
      "CM 26",
      "CM 26.5",
      "CM 27"
    ],
    "available_list": [
      "CM 22",
      "CM 22.5",
      "CM 23",
      "CM 23.5",
      "CM 24",
      "CM 24.5",
      "CM 25",
      "CM 25.5",
      "CM 26",
      "CM 26.5",
      "CM 27"
    ]
  },
  {
    "sku_id": "nike-FD0736-602-Particle_Rose/Tattoo/Light_Violet_Ore/Tattoo",
    "brand": "NIKE",
    "parent_id": "FD0736-602",
    "sku_url": "https://www.nike.com/tw/t/v2k-run-%E5%85%B7%E5%8F%8D%E5%85%89%E8%A3%9D%E9%A3%BE-zJV8TV/FD0736-602",
    "category": "woman_shoes",
    "product_name": "Nike V2K Run",
    "img_path": "https://static.nike.com/a/images/t_default/u_9ddf04c7-2a9a-4d76-add1-d15af8f0263d,c_scale,fl_relative,w_1.0,h_1.0,fl_layer_apply/ba13aa5b-ea70-4f43-a925-2076534a81da/W+NIKE+V2K+RUN.png",
    "color_label": "Particle Rose/Tattoo/Light Violet Ore/Tattoo",
    "original_price": null,
    "current_price": 3800,
    "full_size_list": [
      "CM 22",
      "CM 22.5",
      "CM 23",
      "CM 23.5",
      "CM 24",
      "CM 24.5",
      "CM 25",
      "CM 25.5",
      "CM 26",
      "CM 26.5",
      "CM 27"
    ],
    "available_list": [
      "CM 22",
      "CM 22.5",
      "CM 23",
      "CM 23.5",
      "CM 24",
      "CM 24.5",
      "CM 25",
      "CM 25.5",
      "CM 26",
      "CM 26.5",
      "CM 27"
    ]
  },
  {
    "sku_id": "nike-IO8755-600-Pearl_Pink/白色/Peony",
    "brand": "NIKE",
    "parent_id": "IO8755-600",
    "sku_url": "https://www.nike.com/tw/t/air-force-1-07-valentines-day-lrgg9u9F/IO8755-600",
    "category": "woman_shoes",
    "product_name": "Nike Air Force 1 '07 \"Valentine's Day\"",
    "img_path": "https://static.nike.com/a/images/t_default/u_9ddf04c7-2a9a-4d76-add1-d15af8f0263d,c_scale,fl_relative,w_1.0,h_1.0,fl_layer_apply/516a5c20-9b2e-4bb2-aaa6-439bad85a16a/W+AIR+FORCE+1+%2707.png",
    "color_label": "Pearl Pink/白色/Peony",
    "original_price": null,
    "current_price": 3800,
    "full_size_list": [
      "CM 22",
      "CM 22.5",
      "CM 23",
      "CM 23.5",
      "CM 24",
      "CM 24.5",
      "CM 25",
      "CM 25.5",
      "CM 26",
      "CM 26.5",
      "CM 27"
    ],
    "available_list": [
      "CM 22",
      "CM 22.5",
      "CM 23",
      "CM 23.5",
      "CM 24",
      "CM 24.5",
      "CM 25",
      "CM 25.5",
      "CM 26",
      "CM 26.5",
      "CM 27"
    ]
  },
  {
    "sku_id": "nike-DH3161-100-白色/Desert_Ochre/Team_Orange/黑色",
    "brand": "NIKE",
    "parent_id": "DH3161-100",
    "sku_url": "https://www.nike.com/tw/t/court-legacy-next-nature-rdTfqH/DH3161-100",
    "category": "woman_shoes",
    "product_name": "Nike Court Legacy Next Nature",
    "img_path": "https://static.nike.com/a/images/t_default/u_9ddf04c7-2a9a-4d76-add1-d15af8f0263d,c_scale,fl_relative,w_1.0,h_1.0,fl_layer_apply/46c88fa2-8d40-46ad-8c0c-c40e05776738/WMNS+NIKE+COURT+LEGACY+NN.png",
    "color_label": "白色/Desert Ochre/Team Orange/黑色",
    "original_price": null,
    "current_price": 2700,
    "full_size_list": [
      "CM 22",
      "CM 22.5",
      "CM 23",
      "CM 23.5",
      "CM 24",
      "CM 24.5",
      "CM 25",
      "CM 25.5",
      "CM 26",
      "CM 26.5",
      "CM 27",
      "CM 27.5",
      "CM 28.5"
    ],
    "available_list": [
      "CM 22.5",
      "CM 23",
      "CM 23.5",
      "CM 24",
      "CM 24.5",
      "CM 25",
      "CM 25.5",
      "CM 26",
      "CM 26.5",
      "CM 27.5",
      "CM 28.5"
    ]
  },
  {
    "sku_id": "nike-DH3161-112-Sail/Sanddrift/White_Onyx",
    "brand": "NIKE",
    "parent_id": "DH3161-112",
    "sku_url": "https://www.nike.com/tw/t/court-legacy-next-nature-rdTfqH/DH3161-112",
    "category": "woman_shoes",
    "product_name": "Nike Court Legacy Next Nature",
    "img_path": "https://static.nike.com/a/images/t_default/u_9ddf04c7-2a9a-4d76-add1-d15af8f0263d,c_scale,fl_relative,w_1.0,h_1.0,fl_layer_apply/82780c0b-caf3-4a59-8923-6232e5eb7e5d/WMNS+NIKE+COURT+LEGACY+NN.png",
    "color_label": "Sail/Sanddrift/White Onyx",
    "original_price": null,
    "current_price": 1760,
    "full_size_list": [
      "CM 22",
      "CM 22.5",
      "CM 23",
      "CM 23.5",
      "CM 24",
      "CM 24.5",
      "CM 25",
      "CM 25.5",
      "CM 26",
      "CM 26.5",
      "CM 27",
      "CM 27.5",
      "CM 28",
      "CM 28.5",
      "CM 29"
    ],
    "available_list": [
      "CM 23"
    ]
  },
  {
    "sku_id": "nike-DH3161-114-Pale_Ivory/Chalk/Peony",
    "brand": "NIKE",
    "parent_id": "DH3161-114",
    "sku_url": "https://www.nike.com/tw/t/court-legacy-next-nature-rdTfqH/DH3161-114",
    "category": "woman_shoes",
    "product_name": "Nike Court Legacy Next Nature",
    "img_path": "https://static.nike.com/a/images/t_default/u_9ddf04c7-2a9a-4d76-add1-d15af8f0263d,c_scale,fl_relative,w_1.0,h_1.0,fl_layer_apply/e380b5aa-50e2-4270-ab81-9b6d1672bc6c/WMNS+NIKE+COURT+LEGACY+NN.png",
    "color_label": "Pale Ivory/Chalk/Peony",
    "original_price": null,
    "current_price": 2700,
    "full_size_list": [
      "CM 22",
      "CM 22.5",
      "CM 23",
      "CM 23.5",
      "CM 24",
      "CM 24.5",
      "CM 25",
      "CM 25.5",
      "CM 26",
      "CM 26.5",
      "CM 27",
      "CM 27.5",
      "CM 28.5"
    ],
    "available_list": [
      "CM 22",
      "CM 22.5",
      "CM 23",
      "CM 23.5",
      "CM 24",
      "CM 24.5",
      "CM 25",
      "CM 25.5",
      "CM 26",
      "CM 26.5"
    ]
  },
  {
    "sku_id": "nike-AR3566-002-黑色/Metallic_Hematite/Max_Orange/黑色",
    "brand": "NIKE",
    "parent_id": "AR3566-002",
    "sku_url": "https://www.nike.com/tw/t/shox-tl-jnm2zN/AR3566-002",
    "category": "woman_shoes",
    "product_name": "Nike Shox TL",
    "img_path": "https://static.nike.com/a/images/t_default/u_9ddf04c7-2a9a-4d76-add1-d15af8f0263d,c_scale,fl_relative,w_1.0,h_1.0,fl_layer_apply/f9j2xztqk9bn0ixns8ne/W+NIKE+SHOX+TL.png",
    "color_label": "黑色/Metallic Hematite/Max Orange/黑色",
    "original_price": null,
    "current_price": 5400,
    "full_size_list": [
      "CM 22",
      "CM 22.5",
      "CM 23",
      "CM 23.5",
      "CM 24",
      "CM 24.5",
      "CM 25",
      "CM 25.5",
      "CM 26",
      "CM 26.5",
      "CM 27",
      "CM 28"
    ],
    "available_list": [
      "CM 22.5",
      "CM 23",
      "CM 23.5",
      "CM 24",
      "CM 24.5",
      "CM 25",
      "CM 25.5",
      "CM 26"
    ]
  },
  {
    "sku_id": "nike-AR3566-100-白色/Metallic_Silver/Max_Orange/白色",
    "brand": "NIKE",
    "parent_id": "AR3566-100",
    "sku_url": "https://www.nike.com/tw/t/shox-tl-jnm2zN/AR3566-100",
    "category": "woman_shoes",
    "product_name": "Nike Shox TL",
    "img_path": "https://static.nike.com/a/images/t_default/u_9ddf04c7-2a9a-4d76-add1-d15af8f0263d,c_scale,fl_relative,w_1.0,h_1.0,fl_layer_apply/l1t4slpd4xlbotxs4pyr/W+NIKE+SHOX+TL.png",
    "color_label": "白色/Metallic Silver/Max Orange/白色",
    "original_price": null,
    "current_price": 5400,
    "full_size_list": [
      "CM 22",
      "CM 22.5",
      "CM 23",
      "CM 23.5",
      "CM 24",
      "CM 24.5",
      "CM 25",
      "CM 25.5",
      "CM 26",
      "CM 26.5",
      "CM 27",
      "CM 28"
    ],
    "available_list": [
      "CM 23",
      "CM 23.5",
      "CM 24",
      "CM 24.5",
      "CM 25",
      "CM 25.5",
      "CM 26",
      "CM 26.5"
    ]
  },
  {
    "sku_id": "nike-AR3566-103-Sail/Sail/Sail",
    "brand": "NIKE",
    "parent_id": "AR3566-103",
    "sku_url": "https://www.nike.com/tw/t/shox-tl-jnm2zN/AR3566-103",
    "category": "woman_shoes",
    "product_name": "Nike Shox TL",
    "img_path": "https://static.nike.com/a/images/t_default/u_9ddf04c7-2a9a-4d76-add1-d15af8f0263d,c_scale,fl_relative,w_1.0,h_1.0,fl_layer_apply/79b91cca-ccea-4133-8bd4-a6c33701826d/W+NIKE+SHOX+TL.png",
    "color_label": "Sail/Sail/Sail",
    "original_price": null,
    "current_price": 4320,
    "full_size_list": [
      "CM 22",
      "CM 22.5",
      "CM 23",
      "CM 23.5",
      "CM 24",
      "CM 24.5",
      "CM 25",
      "CM 25.5",
      "CM 26",
      "CM 26.5",
      "CM 27"
    ],
    "available_list": [
      "CM 22",
      "CM 22.5",
      "CM 23",
      "CM 23.5",
      "CM 24",
      "CM 24.5",
      "CM 25",
      "CM 25.5",
      "CM 26",
      "CM 26.5"
    ]
  },
  {
    "sku_id": "nike-AR3566-401-Blue_Tint/Total_Orange/黑色",
    "brand": "NIKE",
    "parent_id": "AR3566-401",
    "sku_url": "https://www.nike.com/tw/t/shox-tl-jnm2zN/AR3566-401",
    "category": "woman_shoes",
    "product_name": "Nike Shox TL",
    "img_path": "https://static.nike.com/a/images/t_default/u_9ddf04c7-2a9a-4d76-add1-d15af8f0263d,c_scale,fl_relative,w_1.0,h_1.0,fl_layer_apply/575cad1b-0f3e-49ad-bc50-c2678710db95/W+NIKE+SHOX+TL.png",
    "color_label": "Blue Tint/Total Orange/黑色",
    "original_price": null,
    "current_price": 3780,
    "full_size_list": [
      "CM 22",
      "CM 22.5",
      "CM 23",
      "CM 23.5",
      "CM 24",
      "CM 24.5",
      "CM 25",
      "CM 25.5",
      "CM 26",
      "CM 26.5",
      "CM 27"
    ],
    "available_list": [
      "CM 22",
      "CM 22.5",
      "CM 23",
      "CM 23.5",
      "CM 24",
      "CM 24.5",
      "CM 25",
      "CM 25.5",
      "CM 26",
      "CM 26.5",
      "CM 27"
    ]
  },
  {
    "sku_id": "nike-AR3566-106-白色/Work_Blue",
    "brand": "NIKE",
    "parent_id": "AR3566-106",
    "sku_url": "https://www.nike.com/tw/t/shox-tl-jnm2zN/AR3566-106",
    "category": "woman_shoes",
    "product_name": "Nike Shox TL",
    "img_path": "https://static.nike.com/a/images/t_default/u_9ddf04c7-2a9a-4d76-add1-d15af8f0263d,c_scale,fl_relative,w_1.0,h_1.0,fl_layer_apply/1574d47c-b101-47d9-89ff-d05b98cc1164/W+NIKE+SHOX+TL.png",
    "color_label": "白色/Work Blue",
    "original_price": null,
    "current_price": 5400,
    "full_size_list": [
      "CM 22",
      "CM 22.5",
      "CM 23",
      "CM 23.5",
      "CM 24",
      "CM 24.5",
      "CM 25",
      "CM 25.5",
      "CM 26",
      "CM 26.5",
      "CM 27"
    ],
    "available_list": [
      "CM 22",
      "CM 22.5",
      "CM 23",
      "CM 23.5",
      "CM 24",
      "CM 24.5",
      "CM 25",
      "CM 25.5",
      "CM 26",
      "CM 26.5",
      "CM 27"
    ]
  },
  {
    "sku_id": "nike-AR3566-203-Linen/Metallic_Silver/Linen",
    "brand": "NIKE",
    "parent_id": "AR3566-203",
    "sku_url": "https://www.nike.com/tw/t/shox-tl-jnm2zN/AR3566-203",
    "category": "woman_shoes",
    "product_name": "Nike Shox TL",
    "img_path": "https://static.nike.com/a/images/t_default/u_9ddf04c7-2a9a-4d76-add1-d15af8f0263d,c_scale,fl_relative,w_1.0,h_1.0,fl_layer_apply/d0a5ffdf-1d44-4396-80c9-9db2b3654ea6/W+NIKE+SHOX+TL.png",
    "color_label": "Linen/Metallic Silver/Linen",
    "original_price": null,
    "current_price": 5400,
    "full_size_list": [
      "CM 22",
      "CM 22.5",
      "CM 23",
      "CM 23.5",
      "CM 24",
      "CM 24.5",
      "CM 25",
      "CM 25.5",
      "CM 26",
      "CM 26.5",
      "CM 27"
    ],
    "available_list": [
      "CM 22",
      "CM 22.5",
      "CM 23",
      "CM 23.5",
      "CM 24",
      "CM 24.5",
      "CM 25",
      "CM 25.5",
      "CM 26",
      "CM 26.5",
      "CM 27"
    ]
  },
  {
    "sku_id": "nike-AR3566-601-Particle_Rose/Metallic_Silver/Particle_Rose",
    "brand": "NIKE",
    "parent_id": "AR3566-601",
    "sku_url": "https://www.nike.com/tw/t/shox-tl-jnm2zN/AR3566-601",
    "category": "woman_shoes",
    "product_name": "Nike Shox TL",
    "img_path": "https://static.nike.com/a/images/t_default/u_9ddf04c7-2a9a-4d76-add1-d15af8f0263d,c_scale,fl_relative,w_1.0,h_1.0,fl_layer_apply/5870189a-c774-4234-9025-403e0d3d062c/W+NIKE+SHOX+TL.png",
    "color_label": "Particle Rose/Metallic Silver/Particle Rose",
    "original_price": null,
    "current_price": 5400,
    "full_size_list": [
      "CM 22",
      "CM 22.5",
      "CM 23",
      "CM 23.5",
      "CM 24",
      "CM 24.5",
      "CM 25",
      "CM 25.5",
      "CM 26",
      "CM 26.5",
      "CM 27"
    ],
    "available_list": [
      "CM 22",
      "CM 22.5",
      "CM 23",
      "CM 23.5",
      "CM 24",
      "CM 24.5",
      "CM 25",
      "CM 25.5",
      "CM 26",
      "CM 26.5",
      "CM 27"
    ]
  },
  {
    "sku_id": "nike-II6282-100-Summit_White/黑色/Metallic_Dark_Grey",
    "brand": "NIKE",
    "parent_id": "II6282-100",
    "sku_url": "https://www.nike.com/tw/t/air-max-muse-N8aTuR5v/II6282-100",
    "category": "woman_shoes",
    "product_name": "Nike Air Max Muse",
    "img_path": "https://static.nike.com/a/images/t_default/u_9ddf04c7-2a9a-4d76-add1-d15af8f0263d,c_scale,fl_relative,w_1.0,h_1.0,fl_layer_apply/46744100-c21a-497c-aa79-161d0a89cfce/WMNS+NIKE+AIR+MAX+MUSE.png",
    "color_label": "Summit White/黑色/Metallic Dark Grey",
    "original_price": null,
    "current_price": 5400,
    "full_size_list": [
      "CM 22",
      "CM 22.5",
      "CM 23",
      "CM 23.5",
      "CM 24",
      "CM 24.5",
      "CM 25",
      "CM 25.5",
      "CM 26",
      "CM 26.5",
      "CM 27",
      "CM 27.5"
    ],
    "available_list": [
      "CM 22",
      "CM 22.5",
      "CM 23",
      "CM 23.5",
      "CM 24",
      "CM 24.5",
      "CM 25",
      "CM 25.5",
      "CM 26",
      "CM 26.5",
      "CM 27"
    ]
  },
  {
    "sku_id": "nike-II6282-500-Tattoo/黑色/Metallic_Dark_Grey/暗粉紅",
    "brand": "NIKE",
    "parent_id": "II6282-500",
    "sku_url": "https://www.nike.com/tw/t/air-max-muse-N8aTuR5v/II6282-500",
    "category": "woman_shoes",
    "product_name": "Nike Air Max Muse",
    "img_path": "https://static.nike.com/a/images/t_default/u_9ddf04c7-2a9a-4d76-add1-d15af8f0263d,c_scale,fl_relative,w_1.0,h_1.0,fl_layer_apply/b3ef04d4-3c1d-4c4f-90bc-fa619b4d8720/WMNS+NIKE+AIR+MAX+MUSE.png",
    "color_label": "Tattoo/黑色/Metallic Dark Grey/暗粉紅",
    "original_price": null,
    "current_price": 5400,
    "full_size_list": [
      "CM 22",
      "CM 22.5",
      "CM 23",
      "CM 23.5",
      "CM 24",
      "CM 24.5",
      "CM 25",
      "CM 25.5",
      "CM 26",
      "CM 26.5",
      "CM 27"
    ],
    "available_list": [
      "CM 22",
      "CM 22.5",
      "CM 23",
      "CM 23.5",
      "CM 24",
      "CM 24.5",
      "CM 25",
      "CM 25.5",
      "CM 26",
      "CM 26.5",
      "CM 27"
    ]
  },
  {
    "sku_id": "nike-IO2400-001-Pure_Platinum/Red_Orbit/白色",
    "brand": "NIKE",
    "parent_id": "IO2400-001",
    "sku_url": "https://www.nike.com/tw/t/reax-8-tr-%E5%81%A5%E8%BA%AB%E8%A8%93%E7%B7%B4-K4q2TBes/IO2400-001",
    "category": "woman_shoes",
    "product_name": "Nike Reax 8 TR",
    "img_path": "https://static.nike.com/a/images/t_default/u_9ddf04c7-2a9a-4d76-add1-d15af8f0263d,c_scale,fl_relative,w_1.0,h_1.0,fl_layer_apply/17619103-7f33-4b25-be48-e91c2350e860/W+NIKE+REAX+8+TR+MESH.png",
    "color_label": "Pure Platinum/Red Orbit/白色",
    "original_price": null,
    "current_price": 2320,
    "full_size_list": [
      "CM 22",
      "CM 22.5",
      "CM 23",
      "CM 23.5",
      "CM 24",
      "CM 24.5",
      "CM 25",
      "CM 25.5",
      "CM 26",
      "CM 26.5",
      "CM 27"
    ],
    "available_list": [
      "CM 22",
      "CM 22.5",
      "CM 23",
      "CM 23.5",
      "CM 24",
      "CM 24.5",
      "CM 25",
      "CM 25.5",
      "CM 26",
      "CM 26.5",
      "CM 27"
    ]
  },
  {
    "sku_id": "nike-IO2400-008-黑色/Anthracite/黑色",
    "brand": "NIKE",
    "parent_id": "IO2400-008",
    "sku_url": "https://www.nike.com/tw/t/reax-8-tr-%E5%81%A5%E8%BA%AB%E8%A8%93%E7%B7%B4-K4q2TBes/IO2400-008",
    "category": "woman_shoes",
    "product_name": "Nike Reax 8 TR",
    "img_path": "https://static.nike.com/a/images/t_default/u_9ddf04c7-2a9a-4d76-add1-d15af8f0263d,c_scale,fl_relative,w_1.0,h_1.0,fl_layer_apply/e86b3cab-8245-4fea-a7ce-1485e7c5e0ed/W+NIKE+REAX+8+TR+MESH.png",
    "color_label": "黑色/Anthracite/黑色",
    "original_price": null,
    "current_price": 2900,
    "full_size_list": [
      "CM 22",
      "CM 22.5",
      "CM 23",
      "CM 23.5",
      "CM 24",
      "CM 24.5",
      "CM 25",
      "CM 25.5",
      "CM 26",
      "CM 26.5",
      "CM 27"
    ],
    "available_list": [
      "CM 22",
      "CM 22.5",
      "CM 23",
      "CM 23.5",
      "CM 24",
      "CM 24.5",
      "CM 25",
      "CM 25.5",
      "CM 26",
      "CM 26.5"
    ]
  },
  {
    "sku_id": "nike-IO2400-100-白色/Sail/Coconut_Milk/白色",
    "brand": "NIKE",
    "parent_id": "IO2400-100",
    "sku_url": "https://www.nike.com/tw/t/reax-8-tr-%E5%81%A5%E8%BA%AB%E8%A8%93%E7%B7%B4-K4q2TBes/IO2400-100",
    "category": "woman_shoes",
    "product_name": "Nike Reax 8 TR",
    "img_path": "https://static.nike.com/a/images/t_default/u_9ddf04c7-2a9a-4d76-add1-d15af8f0263d,c_scale,fl_relative,w_1.0,h_1.0,fl_layer_apply/32f336ca-d74d-49f6-abed-2e3f816cd9d6/W+NIKE+REAX+8+TR+MESH.png",
    "color_label": "白色/Sail/Coconut Milk/白色",
    "original_price": null,
    "current_price": 2900,
    "full_size_list": [
      "CM 22",
      "CM 22.5",
      "CM 23",
      "CM 23.5",
      "CM 24",
      "CM 24.5",
      "CM 25",
      "CM 25.5",
      "CM 26",
      "CM 26.5",
      "CM 27"
    ],
    "available_list": [
      "CM 22",
      "CM 22.5",
      "CM 23",
      "CM 23.5",
      "CM 24",
      "CM 24.5",
      "CM 25",
      "CM 25.5",
      "CM 26",
      "CM 26.5",
      "CM 27"
    ]
  },
  {
    "sku_id": "nike-IO2400-500-Tattoo/Burgundy_Crush",
    "brand": "NIKE",
    "parent_id": "IO2400-500",
    "sku_url": "https://www.nike.com/tw/t/reax-8-tr-%E5%81%A5%E8%BA%AB%E8%A8%93%E7%B7%B4-K4q2TBes/IO2400-500",
    "category": "woman_shoes",
    "product_name": "Nike Reax 8 TR",
    "img_path": "https://static.nike.com/a/images/t_default/u_9ddf04c7-2a9a-4d76-add1-d15af8f0263d,c_scale,fl_relative,w_1.0,h_1.0,fl_layer_apply/f78da737-bfb4-488e-86f0-d1ca8ec5ca94/W+NIKE+REAX+8+TR+MESH.png",
    "color_label": "Tattoo/Burgundy Crush",
    "original_price": null,
    "current_price": 2900,
    "full_size_list": [
      "CM 22",
      "CM 22.5",
      "CM 23",
      "CM 23.5",
      "CM 24",
      "CM 24.5",
      "CM 25",
      "CM 25.5",
      "CM 26",
      "CM 26.5",
      "CM 27"
    ],
    "available_list": [
      "CM 22",
      "CM 22.5",
      "CM 23",
      "CM 23.5",
      "CM 24",
      "CM 24.5",
      "CM 25",
      "CM 25.5",
      "CM 26",
      "CM 26.5",
      "CM 27"
    ]
  }
]